Workbook

Sheet Dashboard
B2: LECICO EGYPT — Financial Ratios Dashboard
B3: Annual Ratios FY 2021 – FY 2025 • Δ YoY column shows change vs. prior year (green = improvement, red = deterioration) • See "Events Log" tab for context behind each year.
B5: 1. LIQUIDITY | K5: 2. PROFITABILITY
B6: Metric | C6: FY-21 | D6: FY-22 | E6: FY-23 | F6: FY-24 | G6: FY-25 | H6: Δ YoY | K6: Metric | L6: FY-21 | M6: FY-22 | N6: FY-23 | O6: FY-24 | P6: FY-25 | Q6: Δ YoY
B7: Current Ratio | C7: ='Ratio Analysis'!F13 -> 1.1375598 | D7: ='Ratio Analysis'!K13 -> 1.1591795 | E7: ='Ratio Analysis'!P13 -> 1.2267967 | F7: ='Ratio Analysis'!U13 -> 1.4928713 | G7: ='Ratio Analysis'!Z13 -> 1.3648887 | H7: =G7-F7 -> -0.12798261 | K7: Gross Margin | L7: ='Ratio Analysis'!F6 -> 0.18290858 | M7: ='Ratio Analysis'!K6 -> 0.18283598 | N7: ='Ratio Analysis'!P6 -> 0.33742528 | O7: ='Ratio Analysis'!U6 -> 0.28221567 | P7: ='Ratio Analysis'!Z6 -> 0.22872483 | Q7: =P7-O7 -> -0.053490841
B8: Quick Ratio | C8: ='Ratio Analysis'!F14 -> 0.52785857 | D8: ='Ratio Analysis'!K14 -> 0.6249191 | E8: ='Ratio Analysis'!P14 -> 0.6208146 | F8: ='Ratio Analysis'!U14 -> 0.61789975 | G8: ='Ratio Analysis'!Z14 -> 0.55490275 | H8: =G8-F8 -> -0.062997001 | K8: EBIT Margin | L8: ='Ratio Analysis'!F7 -> 0.018899623 | M8: ='Ratio Analysis'!K7 -> -0.0095634823 | N8: ='Ratio Analysis'!P7 -> 0.19431724 | O8: ='Ratio Analysis'!U7 -> 0.17321376 | P8: ='Ratio Analysis'!Z7 -> 0.095156259 | Q8: =P8-O8 -> -0.0780575
B9: Cash Ratio | C9: ='Ratio Analysis'!F15 -> 0.11058314 | D9: ='Ratio Analysis'!K15 -> 0.21486866 | E9: ='Ratio Analysis'!P15 -> 0.17313517 | F9: ='Ratio Analysis'!U15 -> 0.12117651 | G9: ='Ratio Analysis'!Z15 -> 0.088287083 | H9: =G9-F9 -> -0.032889424 | K9: Net Profit Margin | L9: ='Ratio Analysis'!F8 -> -0.0088322046 | M9: ='Ratio Analysis'!K8 -> 0.0038882005 | N9: ='Ratio Analysis'!P8 -> 0.097651516 | O9: ='Ratio Analysis'!U8 -> 0.13836468 | P9: ='Ratio Analysis'!Z8 -> 0.033227575 | Q9: =P9-O9 -> -0.1051371
K10: Return on Assets (ROA) | L10: ='Ratio Analysis'!F10 -> -0.0068136986 | M10: ='Ratio Analysis'!K10 -> 0.0027109229 | N10: ='Ratio Analysis'!P10 -> 0.086688078 | O10: ='Ratio Analysis'!U10 -> 0.11867112 | P10: ='Ratio Analysis'!Z10 -> 0.030373212 | Q10: =P10-O10 -> -0.08829791
K11: Return on Equity (ROE) | L11: ='Ratio Analysis'!F11 -> -0.02411066 | M11: ='Ratio Analysis'!K11 -> -0.0017305975 | N11: ='Ratio Analysis'!P11 -> 0.20420163 | O11: ='Ratio Analysis'!U11 -> 0.23840163 | P11: ='Ratio Analysis'!Z11 -> 0.061359018 | Q11: =P11-O11 -> -0.17704261
B24: 3. SOLVENCY / LEVERAGE | K24: 4. CASH FLOW RATIOS
B25: Metric | C25: FY-21 | D25: FY-22 | E25: FY-23 | F25: FY-24 | G25: FY-25 | H25: Δ YoY | K25: Metric | L25: FY-21 | M25: FY-22 | N25: FY-23 | O25: FY-24 | P25: FY-25 | Q25: Δ YoY
B26: Debt-to-Equity | C26: ='Ratio Analysis'!F17 -> 1.2195507 | D26: ='Ratio Analysis'!K17 -> 1.4708539 | E26: ='Ratio Analysis'!P17 -> 1.4120082 | F26: ='Ratio Analysis'!U17 -> 1.0088565 | G26: ='Ratio Analysis'!Z17 -> 1.0792589 | H26: =G26-F26 -> 0.07040233 | K26: OCF Margin | L26: ='Ratio Analysis'!F38 -> -0.0017899378 | M26: ='Ratio Analysis'!K38 -> 0.038292485 | N26: ='Ratio Analysis'!P38 -> 0.028340282 | O26: ='Ratio Analysis'!U38 -> 0.080827852 | P26: ='Ratio Analysis'!Z38 -> -0.02511325 | Q26: =P26-O26 -> -0.1059411
B27: Debt-to-Assets | C27: ='Ratio Analysis'!F18 -> 0.54945837 | D27: ='Ratio Analysis'!K18 -> 0.59528161 | E27: ='Ratio Analysis'!P18 -> 0.58540771 | F27: ='Ratio Analysis'!U18 -> 0.50220437 | G27: ='Ratio Analysis'!Z18 -> 0.51905941 | H27: =G27-F27 -> 0.016855031 | K27: CapEx Coverage | L27: ='Ratio Analysis'!F39 -> -0.07239372 | M27: ='Ratio Analysis'!K39 -> 1.2080588 | N27: ='Ratio Analysis'!P39 -> 0.51907954 | O27: ='Ratio Analysis'!U39 -> 1.8847454 | P27: ='Ratio Analysis'!Z39 -> -0.4198621 | Q27: =P27-O27 -> -2.3046075
B28: Equity Ratio | C28: ='Ratio Analysis'!F19 -> 0.45054163 | D28: ='Ratio Analysis'!K19 -> 0.40471839 | E28: ='Ratio Analysis'!P19 -> 0.41459229 | F28: ='Ratio Analysis'!U19 -> 0.49779563 | G28: ='Ratio Analysis'!Z19 -> 0.48094059 | H28: =G28-F28 -> -0.016855031 | K28: Free Cash Flow (EGP M) | L28: ='Ratio Analysis'!F35/1000000 -> -70.058138 | M28: ='Ratio Analysis'!K35/1000000 -> 21.590451 | N28: ='Ratio Analysis'!P35/1000000 -> -127.16038 | O28: ='Ratio Analysis'!U35/1000000 -> 252.11648 | P28: ='Ratio Analysis'!Z35/1000000 -> -662.73742 | Q28: =P28-O28 -> -914.8539
B43: 5. EARNINGS QUALITY | K43: 6. CASH FLOW BREAKDOWN — الكاش بيروح فين؟
B44: Metric | C44: FY-21 | D44: FY-22 | E44: FY-23 | F44: FY-24 | G44: FY-25 | H44: Δ YoY | K44: Component (EGP M) | L44: FY-21 | M44: FY-22 | N44: FY-23 | O44: FY-24 | P44: FY-25 | Q44: Δ YoY
B45: Cash Realization (OCF/NI) | C45: ='Ratio Analysis'!F37 -> 0.20266036 | D45: ='Ratio Analysis'!K37 -> 9.8483825 | E45: ='Ratio Analysis'!P37 -> 0.29021856 | F45: ='Ratio Analysis'!U37 -> 0.58416536 | G45: ='Ratio Analysis'!Z37 -> -0.75579544 | H45: =G45-F45 -> -1.3399608 | K45: Operating (OCF) | L45: ='Cash Flow'!F39/1000000 -> -4.729391 | M45: ='Cash Flow'!K39/1000000 -> 125.36136 | N45: ='Cash Flow'!P39/1000000 -> 137.25004 | O45: ='Cash Flow'!U39/1000000 -> 537.07583 | P45: ='Cash Flow'!Z39/1000000 -> -195.9756 | Q45: =P45-O45 -> -733.05142
B46: CF Accruals Ratio | C46: ='Ratio Analysis'!F30 -> 0.013707284 | D46: ='Ratio Analysis'!K30 -> -0.0062876077 | E46: ='Ratio Analysis'!P30 -> 0.1124492 | F46: ='Ratio Analysis'!U30 -> 0.078716871 | G46: ='Ratio Analysis'!Z30 -> 0.11324137 | H46: =G46-F46 -> 0.034524498 | K46: Investing (ICF) | L46: ='Cash Flow'!F48/1000000 -> -64.37474 | M46: ='Cash Flow'!K48/1000000 -> -87.103153 | N46: ='Cash Flow'!P48/1000000 -> -235.06152 | O46: ='Cash Flow'!U48/1000000 -> -137.32711 | P46: ='Cash Flow'!Z48/1000000 -> -466.76182 | Q46: =P46-O46 -> -329.43471
B47: BS Accruals Ratio | C47: ='Ratio Analysis'!F31 -> 0.1071703 | D47: ='Ratio Analysis'!K31 -> 0.2051226 | E47: ='Ratio Analysis'!P31 -> 0.17991313 | F47: ='Ratio Analysis'!U31 -> 0.29688725 | G47: ='Ratio Analysis'!Z31 -> 0.15843595 | H47: =G47-F47 -> -0.1384513 | K47: Financing (FCF) | L47: ='Cash Flow'!F57/1000000 -> 120.39135 | M47: ='Cash Flow'!K57/1000000 -> 282.58907 | N47: ='Cash Flow'!P57/1000000 -> 86.117471 | O47: ='Cash Flow'!U57/1000000 -> -503.78451 | P47: ='Cash Flow'!Z57/1000000 -> 624.45385 | Q47: =P47-O47 -> 1128.2384
K48: Net Change in Cash | L48: =L45+L46+L47 -> 51.287214 | M48: =M45+M46+M47 -> 320.84727 | N48: =N45+N46+N47 -> -11.694015 | O48: =O45+O46+O47 -> -104.0358 | P48: =P45+P46+P47 -> -38.283569 | Q48: =P48-O48 -> 65.75223
B62: EXECUTIVE SNAPSHOT — FY-2025 في لمحة
B64: REVENUE GROWTH | D64: NET MARGIN | F64: ROE | H64: DEBT / EQUITY | L64: FCF (EGP M) | N64: CURRENT RATIO
B65: ='Income Statement'!AA6/'Income Statement'!V6-1 -> 0.17442292 | D65: ='Ratio Analysis'!Z8 -> 0.033227575 | F65: ='Ratio Analysis'!Z11 -> 0.061359018 | H65: ='Ratio Analysis'!Z17 -> 1.0792589 | L65: ='Ratio Analysis'!Z35/1000000 -> -662.73742 | N65: ='Ratio Analysis'!Z13 -> 1.3648887
B66: FY-25 vs FY-24 | D66: =IF('Ratio Analysis'!Z8>='Ratio Analysis'!U8,"▲","▼")&" vs "&TEXT('Ratio Analysis'!U8,"0.0%")&" prior" -> ▼ vs 13.8% prior | F66: =IF('Ratio Analysis'!Z11>='Ratio Analysis'!U11,"▲","▼")&" vs "&TEXT('Ratio Analysis'!U11,"0.0%")&" prior" -> ▼ vs 23.8% prior | H66: =IF('Ratio Analysis'!Z17<='Ratio Analysis'!U17,"▼","▲")&" vs "&TEXT('Ratio Analysis'!U17,"0.00")&"x prior" -> ▲ vs 1.01x prior | L66: =IF('Ratio Analysis'!Z35>='Ratio Analysis'!U35,"▲","▼")&" vs "&TEXT('Ratio Analysis'!U35/1000000,"#,##0")&" prior" -> ▼ vs 252 prior | N66: =IF('Ratio Analysis'!Z13>='Ratio Analysis'!U13,"▲","▼")&" vs "&TEXT('Ratio Analysis'!U13,"0.00")&"x prior" -> ▼ vs 1.49x prior
B68: KEY INSIGHTS — FY-2025
B69: • Revenue grew +17.4%, but Net Margin collapsed from 13.8% to 3.3% — severe cost pressure squeezing profitability.
B70: • FCF flipped from +252M to -663M — operations are burning cash (OCF -196M) on top of heavy CapEx.
B71: • D/E rose from 1.01x to 1.08x — the company drew +624M in financing to cover the operating & investing gap.
B72: • Current Ratio dropped from 1.49x to 1.36x — still above 1x, but Cash Ratio at 0.09x signals very tight liquidity.

Sheet Events Log
B2: EVENTS LOG — Lecico Egypt
B3: Track macro events, company decisions, and one-time items that explain each year's performance.
B5: Year | C5: Quarter / Date | D5: Category | E5: Event Description | F5: Impact / Analyst Notes | G5: Affected Metrics | H5: Severity
B6: FY-2021 | C6: Full Year | D6: Recovery | E6: Post-COVID demand recovery; construction sector reopening. | F6: Revenue rebounded but margins still thin due to commodity price volatility. | G6: Revenue, Gross Margin | H6: Low
B7: FY-2022 | C7: 44621 | D7: FX / Macro | E7: EGP devaluation #1 — official rate moved from ~15.7 to ~18.5 EGP/USD. | F7: Imported raw materials & energy costs surged; pricing lagged behind costs. | G7: EBIT Margin, Net Margin, FX losses | H7: High
B8: FY-2022 | C8: 44835 | D8: FX / Macro | E8: EGP devaluation #2 — ~18.5 to ~24.5 EGP/USD. | F8: EBIT Margin turned negative for the year; significant FX-related losses. | G8: EBIT Margin (-1.0%), Net Margin | H8: High
B9: FY-2023 | C9: Full Year | D9: Pricing / Mix | E9: Price hikes passed through; export mix expanded to offset weak EGP. | F9: Gross Margin jumped from 18.3% to 33.7%; EBIT Margin recovered to 19.4%. | G9: Gross Margin (+15ppt), EBIT, ROE (+20ppt) | H9: Positive
B10: FY-2024 | C10: 45352 | D10: FX / Macro | E10: EGP devaluation #3 + IMF deal — EGP moved to ~50 vs USD; rates hiked sharply. | F10: Despite FX shock, pricing power held; FCF turned positive (+252M). | G10: FCF (+), OCF Margin (+8%), Cash Realization | H10: Mixed
B11: FY-2025 | C11: Full Year | D11: Cost Pressure | E11: [TBD] Investigate margin collapse — energy costs? wage inflation? lower export prices? | F11: Net Margin fell 13.8%→3.3%; FCF -663M; OCF turned negative — needs deep dive. | G11: Net Margin (-10.5ppt), FCF, ROE (-17.7ppt) | H11: High

Sheet Income Statement
B1: LECICO EGYPT — Consolidated Income Statement | All Quarters 2021–2025 (EGP)
C2: 2021 | H2: 2022 | M2: 2023 | R2: 2024 | W2: 2025 | AB2: 2020
B3: Item | C3: Q1-2021 | D3: Q2-2021 | E3: Q3-2021 | F3: Q4-2021 | G3: FY-2021 | H3: Q1-2022 | I3: Q2-2022 | J3: Q3-2022 | K3: Q4-2022 | L3: FY-2022 | M3: Q1-2023 | N3: Q2-2023 | O3: Q3-2023 | P3: Q4-2023 | Q3: FY-2023 | R3: Q1-2024 | S3: Q2-2024 | T3: Q3-2024 | U3: Q4-2024 | V3: FY-2024 | W3: Q1-2025 | X3: Q2-2025 | Y3: Q3-2025 | Z3: Q4-2025 | AA3: FY-2025 | AB3: FY-2020
B5: REVENUE
B6: Net Revenue / Sales | C6: 600500902 | D6: 636001960 | E6: 679605545 | F6: 726101330 | G6: =SUM(C$6:F$6) -> 2642209737 | H6: 745522807 | I6: 723286955 | J6: 854605427 | K6: 950369717 | L6: =SUM(H$6:K$6) -> 3273784906 | M6: 1216745149 | N6: 1184485193 | O6: 1218694160 | P6: 1223006708 | Q6: 4842931210 | R6: 1388837366 | S6: 1545783474 | T6: 1925485479 | U6: 1784581295 | V6: 6644687614 | W6: 1690562996 | X6: 1877545324 | Y6: 2174448885 | Z6: 2061116223 | AA6: 7803673428 | AB6: 2055185983
B7: Cost of Sales | C7: -500710130 | D7: -523836117 | E7: -555095897 | F7: -579284761 | G7: =SUM(C7:F7) -> -2158926905 | H7: -593196583 | I7: -587544683 | J7: -741296683 | K7: -753181274 | L7: =SUM(H$7:K$7) -> -2675219223 | M7: -716268069 | N7: -744880803 | O7: -859533984 | P7: -888120919 | Q7: -3208803775 | R7: -953074137 | S7: -1088987615 | T7: -1383964259 | U7: -1343426640 | V7: -4769452651 | W7: -1250122719 | X7: -1428548400 | Y7: -1658952908 | Z7: -1681155536 | AA7: -6018779563 | AB7: -1826019026
B8: GROSS PROFIT | C8: =SUM(C$6:C$7) -> 99790772 | D8: =SUM(D$6:D$7) -> 112165843 | E8: =SUM(E$6:E$7) -> 124509648 | F8: =SUM(F$6:F$7) -> 146816569 | G8: =SUM(C8:F8) -> 483282832 | H8: =SUM(H$6:H$7) -> 152326224 | I8: =SUM(I$6:I$7) -> 135742272 | J8: =SUM(J$6:J$7) -> 113308744 | K8: =SUM(K$6:K$7) -> 197188443 | L8: =SUM(H$8:K$8) -> 598565683 | M8: 500477080 | N8: 439604390 | O8: 359160176 | P8: 334885789 | Q8: 1634127435 | R8: 435763229 | S8: 456795859 | T8: 541521220 | U8: 441154655 | V8: 1875234963 | W8: 440440277 | X8: 448996924 | Y8: 515495977 | Z8: 379960687 | AA8: 1784893865 | AB8: =SUM(AB$6:AB$7) -> 229166957
B9: Gross Margin % | C9: =C$8/C$6 -> 0.16617922 | D9: =D$8/D$6 -> 0.17636084 | E9: =E$8/E$6 -> 0.1832087 | F9: =F$8/F$6 -> 0.20219846 | G9: =G$8/G$6 -> 0.18290858 | H9: =H$8/H$6 -> 0.20432135 | I9: =I$8/I$6 -> 0.18767416 | J9: =J$8/J$6 -> 0.13258603 | ... AB9: =AB$8/AB$6 -> 0.11150668
B10: OPERATING EXPENSES
B11: Other Income | C11: 19541862 | D11: 12278736 | E11: 9700369 | F11: 11821734 | G11: 57842701 | H11: 19859214 | I11: 11173484 | J11: 18075825 | K11: 43175327 | L11: 92283850 | M11: 30015458 | N11: 28532528 | O11: 38886281 | P11: 28336022 | Q11: 125725491 | R11: 52411640 | S11: 33375495 | T11: 3231666 | U11: -14016247 | V11: 75002554 | W11: 8950608 | X11: 8473192 | Y11: 13160319 | Z11: 28028124 | AA11: 58612243 | AB11: 11512021
B12: Distribution & Selling Expenses | C12: -46155681 | D12: -47060286 | E12: -44121438 | F12: -48734684 | G12: -186072089 | H12: -49177557 | I12: -55650661 | J12: -61413009 | K12: -54980619 | L12: -221221846 | M12: -78056800 | N12: -72930711 | O12: -77251047 | P12: -96093146 | Q12: -324331704 | R12: -31265855 | S12: -43780142 | T12: -50870153 | U12: -66085460 | V12: -192001610 | W12: -60700619 | X12: -69363534 | Y12: -73174249 | Z12: -70669690 | AA12: -273908092 | AB12: -126399082
B13: General & Administrative Expenses | C13: -40967517 | D13: -46926201 | E13: -48878654 | F13: -54248019 | G13: -191020391 | H13: -48065894 | I13: -60888236 | J13: -60312234 | K13: -74773257 | L13: -244039621 | M13: -71700181 | N13: -77979092 | O13: -88470972 | P13: -85745391 | Q13: -323895636 | R13: -96173498 | S13: -109053594 | T13: -136380262 | U13: -126564720 | V13: -468172074 | W13: -132813605 | X13: -142823345 | Y13: -146749480 | Z13: -133693112 | AA13: -556079542 | AB13: -150238711
B14: Expected Credit Loss (ECL) | C14: 0 | D14: 0 | E14: 0 | F14: -24945000 | G14: -24945000 | H14: 0 | I14: -7536257 | J14: -4481636 | K14: -8679630 | L14: -42416673 | M14: -2820165 | N14: -8741334 | O14: -9443658 | P14: 3979897 | Q14: -17025260 | R14: -3329490 | S14: -4697879 | T14: 19099072 | U14: -18881811 | V14: -7810108 | W14: -8670192 | X14: -7628108 | Y14: 2803491 | Z14: 10950832 | AA14: -2543977 | AB14: 0
B15: Other Expenses | C15: -21839738 | D15: -27405561 | E15: -31932554 | F15: -3473433 | G15: -89151286 | H15: -44357633 | I15: -59958515 | J15: -99566231 | K15: -32316948 | L15: -214480177 | M15: -71542308 | N15: -33928779 | O15: -23624719 | P15: -24484295 | Q15: -153535304 | R15: -35723940 | S15: -31248978 | T15: -26117203 | U15: -38212288 | V15: -131302409 | W15: -49738946 | X15: -64620676 | Y15: -57374253 | Z15: -96672256 | AA15: -268406131 | AB15: -96492682
B16: EBIT (Operating Profit) | C16: =SUM(C8,C11:C15) -> 10369698 | D16: =SUM(D8,D11:D15) -> 3052531 | E16: =SUM(E8,E11:E15) -> 9277371 | F16: =SUM(F8,F11:F15) -> 27237167 | G16: =SUM(G8,G11:G15) -> 49936767 | H16: =SUM(H8,H11:H15) -> 30584354 | I16: =SUM(I8,I11:I15) -> -37117913 | J16: =SUM(J8,J11:J15) -> -94388541 | ... AB16: =SUM(AB8,AB11:AB15) -> -132451497
B17: EBIT Margin % | C17: =C$16/C$6 -> 0.017268414 | D17: =D$16/D$6 -> 0.0047995623 | E17: =E$16/E$6 -> 0.013651111 | F17: =F$16/F$6 -> 0.037511523 | G17: =G$16/G$6 -> 0.018899623 | H17: =H$16/H$6 -> 0.041024035 | I17: =I$16/I$6 -> -0.051318378 | J17: =J$16/J$6 -> -0.11044692 | ... AB17: =AB$16/AB$6 -> -0.064447451
B18: BELOW THE LINE
B19: Share of Associates / Equity-Accounted Investees | C19: 1126447 | D19: -1195 | E19: -318 | F19: 750188 | G19: 1875122 | H19: 0 | I19: 0 | J19: 0 | K19: 0 | L19: 0 | M19: 0 | N19: 0 | O19: 0 | P19: 0 | Q19: 0 | R19: 0 | S19: 0 | T19: 0 | U19: 995630 | V19: 995630 | W19: 48719 | X19: 8282 | Y19: 7092 | Z19: -2908 | AA19: 61185 | AB19: 0
B20: Net Finance Income / (Expenses) | C20: -13151437 | D20: 1936985 | E20: -3866226 | F20: -3824161 | G20: -18904839 | H20: 21957961 | I20: -2627612 | J20: 102528827 | K20: -14138905 | L20: 107720271 | M20: -129279398 | N20: -39861027 | O20: -78595627 | P20: -6367899 | Q20: -254103950 | R20: 285393803 | S20: -78628736 | T20: -45567076 | U20: -81258767 | V20: 79939224 | W20: -49818485 | X20: -65132430 | Y20: -96883902 | Z20: -69125267 | AA20: -280960084 | AB20: =29894001+(-95394880) -> -65500879
B21: PROFIT BEFORE TAX (PBT) | C21: =SUM(C$16,C$19:C$20) -> -1655292 | D21: =SUM(D$16,D$19:D$20) -> 4988321 | E21: =SUM(E$16,E$19:E$20) -> 5410827 | F21: =SUM(F$16,F$19:F$20) -> 24163194 | G21: =SUM(G$16,G$19:G$20) -> 32907050 | H21: =SUM(H$16,H$19:H$20) -> 52542315 | I21: =SUM(I$16,I$19:I$20) -> -39745525 | J21: =SUM(J$16,J$19:J$20) -> 8140286 | ... AB21: =SUM(AB$16,AB$19:AB$20) -> -197952376
B22: Income Tax Expense | C22: -12501303 | D22: -9214188 | E22: -10281175 | F22: -24246921 | G22: -56243587 | H22: -19210071 | I22: -18056660 | J22: -13423759 | K22: -12991864 | L22: -63682355 | M22: -86536200 | N22: -60085929 | O22: -33060502 | P22: -34358866 | Q22: -214041497 | R22: -120683511 | S22: -61742562 | T22: -71421307 | U22: -58648735 | V22: -312496115 | W22: -54842255 | X22: -52757074 | Y22: -53929398 | Z22: -40843596 | AA22: -202372323 | AB22: =-32344693+7895167 -> -24449526
B23: Effective Tax Rate % | C23: -7.5523249 | D23: 1.8471522 | E23: 1.9001116 | F23: 1.0034651 | G23: 1.7091653 | H23: 0.36561143 | I23: -0.45430674 | J23: 1.6490525 | K23: 0.23419562 | L23: 0.83341337 | M23: 0.48864644 | N23: 0.25601602 | O23: 0.27399621 | P23: 0.22237168 | Q23: 0.31157733 | R23: 0.19879477 | S23: 0.27716826 | T23: 0.23423176 | U23: 0.60381073 | V23: 0.25367288 | W23: 0.37131407 | X23: 0.48889746 | Y23: 0.34287694 | Z23: 0.83736372 | AA23: 0.43834894 | AB23: =IFERROR(IF(OR(AB21=0,ABS(AB22/AB21)>2),NA(),AB22/AB21),NA()) -> 0.12351216
B24: NET PROFIT FOR THE PERIOD | C24: =SUM(C$21:C$22) -> -14156595 | D24: =SUM(D$21:D$22) -> -4225867 | E24: =SUM(E$21:E$22) -> -4870348 | F24: =SUM(F$21:F$22) -> -83727 | G24: =SUM(G$21:G$22) -> -23336537 | H24: =SUM(H$21:H$22) -> 33332244 | I24: =SUM(I$21:I$22) -> -57802185 | J24: =SUM(J$21:J$22) -> -5283473 | ... AB24: =SUM(AB$21:AB$22) -> -222401902
B25: Net Margin % | C25: =C$24/C$6 -> -0.023574644 | D25: =D$24/D$6 -> -0.0066444245 | E25: =E$24/E$6 -> -0.0071664336 | F25: =F$24/F$6 -> -0.00011531035 | G25: =G$24/G$6 -> -0.0088322046 | H25: =H$24/H$6 -> 0.044709892 | I25: =I$24/I$6 -> -0.079915979 | J25: =J$24/J$6 -> -0.0061823537 | ... AB25: =AB$24/AB$6 -> -0.10821498
B26: ATTRIBUTION
B27: Attributable to Shareholders of Holding Company | C27: -16753898 | D27: -6819120 | E27: -8666711 | F27: -4115905 | G27: -36355634 | H27: 29284835 | I27: -60557878 | J27: -9628014 | K27: 37711439 | L27: -3189618 | M27: 89039605 | N27: 167860552 | O27: 78625415 | P27: 110758482 | Q27: 446284054 | R27: 477533848 | S27: 150354721 | T27: 227843495 | U27: 34600844 | V27: 890332908 | W27: 92428628 | X27: 53072222 | Y27: 97110828 | Z27: 1464219 | AA27: 244075897 | AB27: -220605147
B28: Attributable to Non-Controlling Interests (NCI) | C28: 2597303 | D28: 2593253 | E28: 3796363 | F28: 4032178 | G28: 13019097 | H28: 4047409 | I28: 2755693 | J28: 4344541 | K28: 4771108 | L28: 15918750 | M28: 1517881 | N28: 6749494 | O28: 8974517 | P28: 9393629 | Q28: 26635521 | R28: 8858530 | S28: 10664742 | T28: 5652462 | U28: 3881413 | V28: 29057147 | W28: 426874 | X28: 2081009 | Y28: 6244769 | Z28: 6468595 | AA28: 15221247 | AB28: -1796755
B29: Basic & Diluted EPS (EGP per Share) | C29: -0.21 | D29: -0.17 | E29: -0.11 | F29: - | G29: -0.45 | H29: 0.37 | I29: -0.76 | J29: -0.12 | K29: - | L29: -0.04 | M29: 1.11 | N29: - | O29: - | P29: - | Q29: 5.75 | R29: 5.96 | S29: 1.88 | T29: 2.84 | U29: - | V29: 11.12 | W29: 1.16 | X29: 0.66 | Y29: 1.21 | Z29: - | AA29: 3.05 | AB29: -2.76

Sheet Balance Sheet
B1: LECICO EGYPT — Consolidated Balance Sheet | End of Period 2021–2025 (EGP)
C2: 2021 | G2: 2022 | K2: 2023 | O2: 2024 | S2: 2025
B3: Item | C3: Q1-2021 | D3: Q2-2021 | E3: Q3-2021 | F3: FY-2021 | G3: Q1-2022 | H3: Q2-2022 | I3: Q3-2022 | J3: FY-2022 | K3: Q1-2023 | L3: Q2-2023 | M3: Q3-2023 | N3: FY-2023 | O3: Q1-2024 | P3: Q2-2024 | Q3: Q3-2024 | R3: FY-2024 | S3: Q1-2025 | T3: Q2-2025 | U3: Q3-2025 | V3: FY-2025
B5: ASSETS
B6: NON-CURRENT ASSETS
B7: Property, Plant & Equipment (PPE) | C7: 1599642608 | D7: 1576710181 | E7: 1548208036 | F7: 1580363112 | G7: 1579688633 | H7: 1826581231 | I7: 1798331696 | J7: 1985521668 | K7: 2001299000 | L7: 1980703934 | M7: 1978864780 | N7: 2159170561 | O7: 2222670078 | P7: 2201844590 | Q7: 3147953703 | R7: 3322359931 | S7: 3285559758 | T7: 3300464513 | U7: 3289648515 | V7: 3586044267
B8: Projects Under Construction (PUC) | C8: 14227851 | D8: 26742122 | E8: 41489092 | F8: 3956789 | G8: 16818130 | H8: 33649217 | I8: 46226184 | J8: 12066529 | K8: 36486155 | L8: 68066126 | M8: 119719383 | N8: 46977888 | O8: 96499215 | P8: 138654637 | Q8: 182373547 | R8: 55825795 | S8: 221550558 | T8: 260516310 | U8: 320466102 | V8: 72204179
B9: Intangible Assets | C9: 20034229 | D9: 12881799 | E9: 9442887 | F9: 6687265 | G9: 7367773 | H9: 7013961 | I9: 6305706 | J9: 10918162 | K9: 13295908 | L9: 13113267 | M9: 12119965 | N9: 15869154 | O9: 23375009 | P9: 23977327 | Q9: 24621832 | R9: 29719859 | S9: 29281463 | T9: 29102612 | U9: 26362232 | V9: 25139638
B10: Equity-Accounted Investees / Associates | C10: 5867470 | D10: 5856305 | E10: 5867470 | F10: 5871191 | G10: 6816481 | H10: 7017449 | I10: 7296570 | J10: 21977 | K10: 20812 | L10: 20812 | M10: 20812 | N10: 20812 | O10: 20812 | P10: 20812 | Q10: 20812 | R10: 20812 | S10: 69530 | T10: 77812 | U10: 84904 | V10: 81997
B11: Long-Term Notes Receivable | C11: 5693947 | D11: 4334695 | E11: 5663367 | F11: 6085311 | G11: 4050995 | H11: 2054172 | I11: 1077215 | J11: 541578 | K11: 896780 | L11: 215019 | M11: 752396 | N11: 355357 | O11: 345486 | P11: 364191 | Q11: 384130 | R11: 0 | S11: 0 | T11: 0 | U11: 0 | V11: 0
B12: TOTAL NON-CURRENT ASSETS | C12: =SUM(C$7:C$11) -> 1645466105 | D12: =SUM(D$7:D$11) -> 1626525102 | E12: =SUM(E$7:E$11) -> 1610670852 | F12: =SUM(F$7:F$11) -> 1602963668 | G12: =SUM(G$7:G$11) -> 1614742012 | H12: =SUM(H$7:H$11) -> 1876316030 | I12: =SUM(I$7:I$11) -> 1859237371 | J12: =SUM(J$7:J$11) -> 2009069914 | ... V12: =SUM(V$7:V$11) -> 3683470081
B13: CURRENT ASSETS
B14: Inventories | C14: 870524220 | D14: 965305447 | E14: 996838803 | F14: 976532151 | G14: 1023172899 | H14: 1090914499 | I14: 1057251513 | J14: 1238161960 | K14: 1548020917 | L14: 1796877024 | M14: 1762795802 | N14: 1596967107 | O14: 1821570697 | P14: 2137776182 | Q14: 2338788769 | R14: 2543351777 | S14: 2599505753 | T14: 2727122212 | U14: 2851411177 | V14: 2880321793
B15: Trade & Other Receivables | C15: 685651605 | D15: 756797683 | E15: 751158633 | F15: 668332043 | G15: 759549990 | H15: 808947883 | I15: 892330222 | J15: 950302178 | K15: 1087337975 | L15: 1200477567 | M15: 1209389387 | N15: 1179786142 | O15: 1438677672 | P15: 1516852201 | Q15: 1611094132 | R15: 1443866262 | S15: 1599602145 | T15: 1814733919 | U15: 1709498906 | V15: 1659292035
B16: Investment in Fair Value through P/L | C16: - | D16: - | E16: - | F16: - | G16: - | H16: - | I16: - | J16: - | K16: - | L16: - | M16: - | N16: - | O16: - | P16: - | Q16: 167900327 | R16: - | S16: - | T16: - | U16: - | V16: -
B17: Cash & Cash Equivalents | C17: 154670438 | D17: 155770979 | E17: 145331805 | F17: 177116247 | G17: 296031804 | H17: 285000492 | I17: 452365350 | J17: 497963520 | K17: 327967960 | L17: 311063251 | M17: 320036269 | N17: 456269505 | O17: 722572696 | P17: 491094061 | Q17: 662068282 | R17: 352233706 | S17: 354038672 | T17: 353936318 | U17: 350667194 | V17: 313950137
B18: TOTAL CURRENT ASSETS | C18: =SUM(C$14:C$17) -> 1710846263 | D18: =SUM(D$14:D$17) -> 1877874109 | E18: =SUM(E$14:E$17) -> 1893329241 | F18: =SUM(F$14:F$17) -> 1821980441 | G18: =SUM(G$14:G$17) -> 2078754693 | H18: =SUM(H$14:H$17) -> 2184862874 | I18: =SUM(I$14:I$17) -> 2401947085 | J18: =SUM(J$14:J$17) -> 2686427658 | ... V18: =SUM(V$14:V$17) -> 4853563965
B19: TOTAL ASSETS | C19: =SUM(C$18,C$12) -> 3356312368 | D19: =SUM(D$18,D$12) -> 3504399211 | E19: =SUM(E$18,E$12) -> 3504000093 | F19: =SUM(F$18,F$12) -> 3424944109 | G19: =SUM(G$18,G$12) -> 3693496705 | H19: =SUM(H$18,H$12) -> 4061178904 | I19: =SUM(I$18,I$12) -> 4261184456 | J19: =SUM(J$18,J$12) -> 4695497572 | ... V19: =SUM(V$18,V$12) -> 8537034046
B20: EQUITY & LIABILITIES
B21: EQUITY
B22: Issued & Paid-Up Capital | C22: 400000000 | D22: 400000000 | E22: 400000000 | F22: 400000000 | G22: 400000000 | H22: 400000000 | I22: 400000000 | J22: 400000000 | K22: 400000000 | L22: 400000000 | M22: 400000000 | N22: 400000000 | O22: 400000000 | P22: 400000000 | Q22: 400000000 | R22: 400000000 | S22: 400000000 | T22: 400000000 | U22: 400000000 | V22: 400000000
B23: Treasury Shares | C23: 0 | D23: 0 | E23: 0 | F23: 0 | G23: 0 | H23: 0 | I23: 0 | J23: 0 | K23: 0 | L23: -25388998 | M23: -25388998 | N23: -25388998 | O23: 0 | P23: 0 | Q23: 0 | R23: 0 | S23: 0 | T23: 0 | U23: 0 | V23: 0
B24: Reserves | C24: 1432583378 | D24: 1435504915 | E24: 1440844903 | F24: 1442060456 | G24: 1471858015 | H24: 1769229643 | I24: 1772911677 | J24: 1813887128 | K24: 1750238711 | L24: 1745246738 | M24: 1733028098 | N24: 1735425623 | O24: 1818481801 | P24: 1829669152 | Q24: 2379040510 | R24: 2394178238 | S24: 2419094457 | T24: 2420832381 | U24: 2412913569 | V24: 2414837399
B25: Retained Earnings / (Accumulated Losses) | C25: -297839234 | D25: -297839234 | E25: -297839234 | F25: -297839234 | G25: -334194868 | H25: -324393877 | I25: -333940000 | J25: -367624208 | K25: -370813826 | L25: -370813826 | M25: -35288254 | N25: 75470228 | O25: 527615078 | P25: 677969799 | Q25: 905813294 | R25: 940414138 | S25: 1011347846 | T25: 1064420052 | U25: 1161530880 | V25: 1162995099
B26: Net P/L for the period/year | C26: -16753898 | D26: -23573018 | E26: -32239729 | F26: -36355634 | G26: 29284835 | H26: -31273043 | I26: -40901057 | J26: -3189618 | K26: 89039605 | L26: 256900157 | M26: - | N26: - | O26: - | P26: - | Q26: - | R26: - | S26: - | T26: - | U26: - | V26: -
B27: Equity Attributable to Holding Company | C27: =SUM(C22:C26) -> 1517990246 | D27: =SUM(D22:D26) -> 1514092663 | E27: =SUM(E22:E26) -> 1510765940 | F27: =SUM(F22:F26) -> 1507865588 | G27: =SUM(G22:G26) -> 1566947982 | H27: =SUM(H22:H26) -> 1813562723 | I27: =SUM(I22:I26) -> 1798070620 | J27: =SUM(J22:J26) -> 1843073302 | ... V27: =SUM(V22:V26) -> 3977832498
B28: Non-Controlling Interests (NCI) | C28: 35251044 | D28: 36427793 | E28: 30910600 | F28: 35214304 | G28: 32758810 | H28: 41642829 | I28: 44315864 | J28: 57280922 | K28: 54654010 | L28: 62122761 | M28: 69051324 | N28: 76266769 | O28: 94153152 | P28: 95744125 | Q28: 118351860 | R28: 122018569 | S28: 121277350 | T28: 122305261 | U28: 121012528 | V28: 127973731
B29: TOTAL EQUITY | C29: =SUM(C$27:C$28) -> 1553241290 | D29: =SUM(D$27:D$28) -> 1550520456 | E29: =SUM(E$27:E$28) -> 1541676540 | F29: =SUM(F$27:F$28) -> 1543079892 | G29: =SUM(G$27:G$28) -> 1599706792 | H29: =SUM(H$27:H$28) -> 1855205552 | I29: =SUM(I$27:I$28) -> 1842386484 | J29: =SUM(J$27:J$28) -> 1900354224 | ... V29: =SUM(V$27:V$28) -> 4105806229
B30: NON-CURRENT LIABILITIES
B31: Long-Term Loans | C31: 30067785 | D31: 25215804 | E31: 20401547 | F31: 25034918 | G31: 22929806 | H31: 17783883 | I31: 12432030 | J31: 8240932 | K31: 790033 | L31: 630578 | M31: 362273 | N31: 164614 | O31: 0 | P31: 0 | Q31: 0 | R31: 0 | S31: 0 | T31: 0 | U31: 0 | V31: 0
B32: Non-Current Portion of Lease Liabilities | C32: 1209526 | D32: 1164776 | E32: 55758447 | F32: 56066868 | G32: 53333852 | H32: 58103084 | I32: 52554813 | J32: 71523861 | K32: 85935792 | L32: 86866743 | M32: 83905366 | N32: 84977704 | O32: 117422471 | P32: 111802839 | Q32: 125126224 | R32: 107706551 | S32: 102354764 | T32: 125384366 | U32: 123419848 | V32: 111403877
B33: Long-Term Notes Payable | C33: 0 | D33: 24998784 | E33: 159233119 | F33: 177376553 | G33: 201343118 | H33: 219625017 | I33: 238825714 | J33: 265622137 | K33: 305181530 | L33: 337069529 | M33: 334899508 | N33: 335209954 | O33: 337036619 | P33: 332679398 | Q33: 393985235 | R33: 355887441 | S33: 339877698 | T33: 310217456 | U33: 275956921 | V33: 236859693
B34: Provisions — Non-Current | C34: 7767604 | D34: 8234210 | E34: 8994985 | F34: 8371135 | G34: 9960870 | H34: 11007507 | I34: 13083805 | J34: 21349926 | K34: 10060744 | L34: 12234456 | M34: 13878505 | N34: 14420148 | O34: 16968353 | P34: 18850107 | Q34: 20676349 | R34: 0 | S34: 9572532 | T34: 13344256 | U34: 0 | V34: 0
B35: Deferred Tax Liabilities | C35: 13603785 | D35: 13123053 | E35: 11851492 | F35: 13357906 | G35: 12842982 | H35: 10990029 | I35: 9398603 | J35: 110881391 | K35: 111445900 | L35: 111657081 | M35: 110843028 | N35: 123533546 | O35: 118020873 | P35: 115920882 | Q35: 518836142 | R35: 520391057 | S35: 520722675 | T35: 518035545 | U35: 516549610 | V35: 526949846
B36: TOTAL NON-CURRENT LIABILITIES | C36: =SUM(C$31:C$35) -> 52648700 | D36: =SUM(D$31:D$35) -> 72736627 | E36: =SUM(E$31:E$35) -> 256239590 | F36: =SUM(F$31:F$35) -> 280207380 | G36: =SUM(G$31:G$35) -> 300410628 | H36: =SUM(H$31:H$35) -> 317509520 | I36: =SUM(I$31:I$35) -> 326294965 | J36: =SUM(J$31:J$35) -> 477618247 | ... R36: =SUM(R$31:R$35) -> 983985049 | S36: 972527669 | T36: 966981623 | U36: 915926379 | V36: =SUM(V$31:V$35) -> 875213416
B37: CURRENT LIABILITIES
B38: Banks Credit Facilities / Overdraft | C38: 743937136 | D38: 865932136 | E38: 881749265 | F38: 823948627 | G38: 905813120 | H38: 1058684276 | I38: 1107336838 | J38: 1247271122 | K38: 1395300200 | L38: 1531329751 | M38: 1477390146 | N38: 1387483248 | O38: 1198532328 | P38: 1244420277 | Q38: 1390411860 | R38: 918482312 | S38: 1402073044 | T38: 1884198508 | U38: 1585260675 | V38: 1587533130
B39: Accrued Income Tax | C39: 0 | D39: 0 | E39: 0 | F39: 39950980 | G39: 0 | H39: 0 | I39: 0 | J39: 41393653 | K39: 103000127 | L39: 137785028 | M39: 137938983 | N39: 151554607 | O39: 271517615 | P39: 165335386 | Q39: 228034445 | R39: 280295448 | S39: 323007229 | T39: 92412369 | U39: 132076770 | V39: 147720552
B40: Loans — Current Portion | C40: 85518032 | D40: 18816000 | E40: 23565000 | F40: 14148000 | G40: 22425775 | H40: 23050402 | I40: 23915236 | J40: 30338673 | K40: 37971784 | L40: 28638548 | M40: 19384464 | N40: 10158729 | O40: 1287576 | P40: 990570 | Q40: 706176 | R40: 344005 | S40: 0 | T40: 0 | U40: 0 | V40: 0
B41: Short Term Liability | C41: 0 | D41: 0 | E41: 0 | F41: 0 | G41: 10920458 | H41: 12797974 | I41: 11675405 | J41: 16424592 | K41: 20637876 | L41: 20921839 | M41: 22005090 | N41: 23801960 | O41: 36114885 | P41: 35858213 | Q41: 38810138 | R41: 35443162 | S41: 34086377 | T41: 38155448 | U41: 39979581 | V41: 40232181
B42: Trade & Other Payables | C42: 919086789 | D42: 924819473 | E42: 756875814 | F42: 673725980 | G42: 825465293 | H42: 762493347 | I42: 911085196 | J42: 933175828 | K42: 966244818 | L42: 976095526 | M42: 997252859 | N42: 954269904 | O42: 1269087921 | P42: 1362026631 | Q42: 1495177081 | R42: 1511358852 | S42: 1237093673 | T42: 1311841012 | U42: 1566047785 | V42: 1520387559
B43: Provisions — Current | C43: 1880421 | D43: 379996 | E43: 32030200 | F43: 28057917 | G43: 28754639 | H43: 31437833 | I43: 38490332 | J43: 48921233 | K43: 55638203 | L43: 59241089 | M43: 64436402 | N43: 108068490 | O43: 119492993 | P43: 119316622 | Q43: 120236220 | R43: 160858369 | S43: 169100234 | T43: 184807042 | U43: 213390863 | V43: 260140979
B44: TOTAL CURRENT LIABILITIES | C44: =SUM(C$38:C$43) -> 1750422378 | D44: 1881142128 | E44: 1706083963 | F44: 1601656837 | G44: =SUM(G$38:G$43) -> 1793379285 | H44: =SUM(H$38:H$43) -> 1888463832 | I44: =SUM(I$38:I$43) -> 2092503007 | J44: =SUM(J$38:J$43) -> 2317525101 | K44: =SUM(K$38:K$43) -> 2578793008 | L44: =SUM(L$38:L$43) -> 2754011781 | M44: =SUM(M$38:M$43) -> 2718407944 | N44: =SUM(N$38:N$43) -> 2635336938 | ... V44: =SUM(V$38:V$43) -> 3556014401
B45: TOTAL LIABILITIES | C45: =C$44+C$36 -> 1803071078 | D45: 1953878755 | E45: 1962323553 | F45: 1881864217 | G45: =SUM(G$44,G$36) -> 2093789913 | H45: =SUM(H$44,H$36) -> 2205973352 | I45: =SUM(I$44,I$36) -> 2418797972 | J45: =SUM(J$44,J$36) -> 2795143348 | K45: =SUM(K$44,K$36) -> 3092207007 | L45: =SUM(L$44,L$36) -> 3302470168 | M45: =SUM(M$44,M$36) -> 3262296624 | N45: =SUM(N$44,N$36) -> 3193642904 | ... V45: =SUM(V$44,V$36) -> 4431227817
B46: TOTAL EQUITY & LIABILITIES | C46: =SUM(C$45,C$29) -> 3356312368 | D46: =SUM(D$45,D$29) -> 3504399211 | E46: =SUM(E$45,E$29) -> 3504000093 | F46: =SUM(F$45,F$29) -> 3424944109 | G46: =SUM(G$45,G$29) -> 3693496705 | H46: =SUM(H$45,H$29) -> 4061178904 | I46: =SUM(I$45,I$29) -> 4261184456 | J46: =SUM(J$45,J$29) -> 4695497572 | ... V46: =SUM(V$45,V$29) -> 8537034046
C47: =SUM(C$19-C$46) -> 0 | D47: =SUM(D$19-D$46) -> 0 | E47: =SUM(E$19-E$46) -> 0 | F47: =SUM(F$19-F$46) -> 0 | G47: =SUM(G$19-G$46) -> 0 | H47: =SUM(H$19-H$46) -> 0 | I47: =SUM(I$19-I$46) -> 0 | J47: =SUM(J$19-J$46) -> 0 | ... V47: =SUM(V$19-V$46) -> 0

Sheet Cash Flow
A1: LECICO EGYPT — Consolidated Cash Flow | All Quarters 2021–2025 (EGP)
A2: Item | B2: 2021 | G2: 2022 | L2: 2023 | Q2: 2024 | V2: 2025 | AB2: 2020
B3: Q1 | C3: Q2 | D3: Q3 | E3: Q4 | F3: FY | G3: Q1 | H3: Q2 | I3: Q3 | J3: Q4 | K3: FY | L3: Q1 | M3: Q2 | N3: Q3 | O3: Q4 | P3: FY | Q3: Q1 | R3: Q2 | S3: Q3 | T3: Q4 | U3: FY | V3: Q1 | W3: Q2 | X3: Q3 | Y3: Q4 | Z3: FY | AB3: FY-2020
A4: Cash Flow from Operating Activities
A5: Net profit/(loss) for the period before tax | B5: -1655292 | C5: 4988321 | D5: 5410827 | E5: 24163194 | F5: 32907050 | G5: 52542315 | H5: -39745525 | I5: 8140286 | J5: 55474411 | K5: 76411487 | L5: 177093686 | M5: 234695975 | N5: 120660434 | O5: 154510977 | P5: 686961072 | Q5: 607075889 | R5: 222762025 | S5: 304917264 | T5: 97130992 | U5: 1231886170 | V5: 147697757 | W5: 107910305 | X5: 157284995 | Y5: 48776410 | Z5: 461669467 | AB5: -220605147
A6: Adjustments for non-cash items:
A7: Property, plant & equipment depreciation | B7: 30379884 | C7: 28832771 | D7: 29846313 | E7: 26148931 | F7: =SUM(B7:E7) -> 115207899 | G7: 34750995 | H7: 19901347 | I7: 27142044 | J7: 27679306 | K7: 109473692 | L7: 27627447 | M7: 28411843 | N7: 27842779 | O7: 31849190 | P7: 115731259 | Q7: 39426629 | R7: 43161665 | S7: 43985474 | T7: 48400090 | U7: 174973858 | V7: 56500004 | W7: 55333196 | X7: 58865473 | Y7: 62701812 | Z7: 233400485 | AB7: 102610286
A8: Intangible assets amortization | B8: 174182 | C8: 185156 | D8: 382381 | E8: 237392 | F8: =SUM(B8:E8) -> 979111 | G8: 113009 | H8: 45484 | I8: 254105 | J8: 765942 | K8: 1178540 | L8: 513550 | M8: 554905 | N8: 1056542 | O8: 329332 | P8: 2454329 | Q8: 655989 | R8: 1005085 | S8: 1000695 | T8: 1406381 | U8: 4068150 | V8: 1194618 | W8: 1247267 | X8: 1225054 | Y8: 1144315 | Z8: 4811254 | AB8: 1033837
A9: Formed provisions | B9: 13970725 | C9: 20130164 | D9: -31550889 | E9: 6150000 | F9: =SUM(B9:E9) -> 8700000 | AB9: 67411894
A10: Provisions reversed / no longer used | D10: -4500000 | E10: -1370197 | F10: =SUM(B10:E10) -> -5870197
A11: Employees' share in profit | B11: 17742380 | C11: 17723247 | D11: 17732814 | E11: -53198441 | AB11: 60673852
A12: Finance interest expenses on lease contracts | E12: 1669361 | F12: =SUM(B12:E12) -> 1669361 | J12: 3167892 | K12: 3167892 | L12: 846785 | M12: 1165257 | N12: 1876182 | O12: 1163773 | P12: 5051997 | Q12: 1334200 | R12: 7512611 | S12: 662752 | T12: -1737604 | U12: 7771959 | V12: 1549797 | W12: 12684881 | X12: -8076758 | Y12: 2397287 | Z12: 8555207
A13: Finance expenses | E13: 76773124 | F13: =SUM(B13:E13) -> 76773124 | J13: 101946625 | K13: 101946625 | M13: 105433898 | N13: 65066392 | O13: 73246767 | P13: 243747057 | Q13: 68136917 | R13: 75701768 | S13: 60564107 | T13: 69700293 | U13: 274103085 | V13: 59713766 | W13: 74652506 | X13: 90797602 | Y13: 64796959 | Z13: 289960833
A14: Interest income | E14: -3840095 | F14: =SUM(B14:E14) -> -3840095 | J14: -4980868 | K14: -4980868 | S14: -4812191 | T14: -2058752 | U14: -6870943 | V14: -416077 | W14: -1380375 | X14: -1726445 | Y14: 2415343 | Z14: -1107554
A15: Losses / (gains) on hedge contracts | E15: -30431181 | F15: =SUM(B15:E15) -> -30431181 | J15: 104213713 | K15: 104213713
A16: Capital gain / (loss) | D16: -70000 | E16: -39679 | F16: =SUM(B16:E16) -> -109679 | H16: 26369308 | I16: 88205 | J16: 630105 | K16: 27087618 | L16: -1285472 | M16: -1084944 | N16: -400000 | O16: 0 | P16: -2770416 | T16: -15007 | U16: -15007 | AB16: -217699
A17: Net income from investment fair value through P&L | O17: -29738182 | P17: -29738182 | Q17: -149513068 | R17: 0 | S17: -982291 | T17: -3310601 | U17: -153805960
A18: Impairment of intangible assets | C18: 7500000 | D18: 3750000 | E18: 3750000 | F18: =SUM(B18:E18) -> 15000000 | AB18: 9332380
A19: Impairment loss of trade and other receivables | B19: 4500000 | C19: 3400000 | D19: 10600000 | E19: 6445000 | F19: =SUM(B19:E19) -> 24945000 | G19: 21719150 | H19: -21719150
A20: Impairment in equity-accounted investees | J20: 6924716 | K20: 6924716
A21: Reversal of inventory write-off | E21: 5194831 | F21: =SUM(B21:E21) -> 5194831
A22: Differences from PV of long-term notes receivable | B22: -408430 | C22: -415748 | D22: 246328 | E22: -21944 | F22: =SUM(B22:E22) -> -599794 | G22: -290684 | H22: -253177 | I22: -123044 | J22: 666905 | AB22: -3949302
A23: Differences from PV of long-term notes payable | C23: -8420754 | D23: -47888558 | E23: 56309312 | G23: -7479722 | H23: -6385333 | I23: -6255051 | J23: 20120106
A24: Foreign currency translation differences | S24: -219802796 | T24: 219802796 | W24: -31853583 | X24: 15889503 | Y24: 15964080
A25: Change in translation reserve and FX differences | B25: -183267 | C25: 2732822 | D25: -3798031 | E25: 1551963 | F25: =SUM(B25:E25) -> 303487 | H25: 32240411 | I25: 21161831 | J25: 69969929 | K25: 123372171 | L25: -137789964 | M25: -121442705 | N25: -98052778 | O25: -3658739 | P25: -360944186 | Q25: 122402303 | R25: -97801 | S25: -122304502 | T25: -201137365 | U25: -201137365 | V25: -11029001 | W25: 11029001 | Y25: -16448402 | Z25: -16448402 | AB25: 7175132
A26: Profit generated from operations | B26: =B5+SUM(B7:B25) -> 64520182 | C26: =C5+SUM(C7:C25) -> 76655979 | D26: =D5+SUM(D7:D25) -> -19838815 | E26: =E5+SUM(E7:E25) -> 119491571 | F26: =SUM(B26:E26) -> 240828917 | G26: =G5+SUM(G7:G25) -> 101355063 | H26: =H5+SUM(H7:H25) -> 10453365 | I26: =I5+SUM(I7:I25) -> 50408376 | J26: =J5+SUM(J7:J25) -> 386578782 | K26: =K5+SUM(K7:K25) -> 548795586 | L26: =L5+SUM(L7:L25) -> 67006032 | M26: =M5+SUM(M7:M25) -> 247734229 | N26: =N5+SUM(N7:N25) -> 118049551 | ... Z26: =Z5+SUM(Z7:Z25) -> 980841290 | AB26: =AB5+SUM(AB7:AB25)+(32344693-8107168)+1142269-25044 -> 48819983
A27: Working capital changes:
A28: Change in inventories | B28: -36856249 | C28: -94758124 | D28: -31556459 | E28: 15096422 | F28: =SUM(B28:E28) -> -148074410 | G28: -40824583 | H28: -76174353 | I28: 24350349 | J28: -205195922 | K28: -297844509 | L28: -374111193 | M28: -125087900 | N28: 112200246 | O28: 159812434 | P28: -227186413 | Q28: -293966912 | R28: -316161043 | S28: -200482262 | T28: -214418525 | U28: -1025028742 | V28: -57258352 | W28: -131779108 | X28: -131637314 | Y28: -28910616 | Z28: -349585390 | AB28: 111597065
A29: Change in trade, notes and other receivables | B29: -59312981 | C29: -69351383 | D29: -6455641 | E29: 72630621 | F29: =SUM(B29:E29) -> -62489384 | G29: -132000726 | H29: -15896490 | I29: -85961603 | J29: -53047768 | K29: -286906587 | L29: -20672257 | M29: -112829497 | N29: -9518392 | O29: 116006837 | P29: -27013309 | Q29: -263362136 | R29: -78415475 | S29: 115960027 | T29: -42681233 | U29: -268498817 | V29: -155807220 | W29: -214720217 | X29: 105709675 | Y29: 50261745 | Z29: -214556017 | AB29: 27368933
A30: Change in trade, notes and other payables | B30: 68965658 | C30: 35700473 | D30: 95307558 | E30: -42620336 | F30: =SUM(B30:E30) -> 157353353 | G30: 152945094 | H30: -45466243 | I30: 140424758 | J30: 85957859 | K30: 333861468 | L30: 56954985 | M30: 41824760 | N30: 18911324 | O30: -76843911 | P30: 40847158 | Q30: 316644682 | R30: 88581489 | S30: 338677000 | T30: 196487698 | U30: 940390869 | V30: -276389720 | W30: 72603131 | X30: 201556523 | Y30: -83931109 | Z30: -86161175 | AB30: 229489994
A31: Change in provisions / Utilized provisions | B31: -11420300 | C31: 11420300 | E31: -7320852 | F31: =SUM(B31:E31) -> -7320852 | G31: 1596722 | H31: -188763 | I31: 8689256 | J31: 19578317 | K31: 29675532 | L31: 9331258 | M31: 5625614 | N31: 6749153 | O31: 44206402 | P31: 65912427 | Q31: 12324503 | R31: 1623629 | S31: 2719598 | T31: 18935189 | U31: 35602919 | V31: 17863604 | W31: 19733841 | X31: 14935049 | Y31: 46750116 | Z31: 99282610
A32: Payments of employees dividend | D32: -68524899 | E32: 26024899 | F32: =SUM(B32:E32) -> -42500000 | J32: -46777535 | K32: -46777535 | O32: -85610048 | P32: -85610048
A33: Cash generated from operations before interest & tax | B33: =B26+SUM(B28:B32) -> 25896310 | C33: =C26+SUM(C28:C32) -> -40332755 | D33: =D26+SUM(D28:D32) -> -31068256 | E33: =E26+SUM(E28:E32) -> 183302325 | F33: =SUM(B33:E33) -> 137797624 | G33: =G26+SUM(G28:G32) -> 83071570 | H33: =H26+SUM(H28:H32) -> -127272484 | I33: =I26+SUM(I28:I32) -> 137911136 | J33: =J26+SUM(J28:J32) -> 187093733 | K33: =K26+SUM(K28:K32) -> 280803955 | L33: =L26+SUM(L28:L32) -> -261491175 | M33: =M26+SUM(M28:M32) -> 57267206 | N33: =N26+SUM(N28:N32) -> 246391882 | ... Z33: =Z26+SUM(Z28:Z32) -> 429821318 | AB33: =AB26+SUM(AB28:AB32) -> 417275975
A34: Proceeds from interest income | E34: 3840095 | F34: =SUM(B34:E34) -> 3840095 | J34: 4980868 | K34: 4980868 | S34: 4812191 | T34: 2058752 | U34: 6870943 | V34: 416077 | W34: 1380375 | X34: 1726445 | Y34: -2415343 | Z34: 1107554
A35: Interest / Finance expenses paid | E35: -78442485 | F35: =SUM(B35:E35) -> -78442485 | J35: -105114517 | K35: -105114517 | M35: -107445940 | N35: -66942574 | O35: -69358543 | P35: -243747057 | Q35: -68136917 | R35: -84548579 | S35: -51717296 | T35: -69700293 | U35: -274103085 | V35: -59713766 | W35: -74652506 | X35: -90797602 | Y35: -64796959 | Z35: -289960833
A36: Finance interest paid on lease contracts | M36: 846785 | O36: -5051997 | P36: -5051997 | Q36: -1334200 | R36: 1334200 | S36: -9509563 | T36: 1737604 | U36: -7771959 | V36: -1549797 | W36: -12684881 | X36: 8076758 | Y36: -2397287 | Z36: -8555207
A37: Income tax paid | B37: -4370803 | C37: -25129229 | D37: -5644465 | E37: -22629473 | F37: =SUM(B37:E37) -> -57773970 | G37: -14085191 | H37: -32889830 | I37: 1816742 | J37: -10150666 | K37: -55308945 | L37: -8691819 | M37: -25175900 | N37: -33644612 | O37: 26118678 | P37: -41393653 | Q37: -6233176 | R37: -170024782 | S37: -9575106 | T37: -15527184 | U37: -201360248 | V37: -11798856 | W37: -286039064 | X37: -15750932 | Y37: -14799578 | Z37: -328388430 | AB37: -25415298
A38: Utilized provisions | C38: -32573450 | D38: 32073450 | E38: -9650655 | F38: =SUM(B38:E38) -> -10150655 | AB38: -39206423
A39: Net cash from / (used in) operating activities | B39: =B33+SUM(B34:B38) -> 21525507 | C39: =C33+SUM(C34:C38) -> -98035434 | D39: =D33+SUM(D34:D38) -> -4639271 | E39: =E33+SUM(E34:E38) -> 76419807 | F39: =F33+SUM(F34:F38) -> -4729391 | G39: =G33+SUM(G34:G38) -> 68986379 | H39: =H33+SUM(H34:H38) -> -160162314 | I39: =I33+SUM(I34:I38) -> 139727878 | ... Z39: =Z33+SUM(Z34:Z38) -> -195975598 | AB39: =AB33+SUM(AB34:AB38) -> 352654254
A40: Cash Flow from Investing Activities
A41: Payments for acquisition of PPE & PUC | B41: -10048996 | C41: -18414616 | D41: -16091138 | E41: -20773997 | F41: =SUM(B41:E41) -> -65328747 | G41: -29707526 | H41: -16028118 | I41: -9610366 | J41: -48424900 | K41: -103770910 | L41: -35403060 | M41: -39477604 | N41: -67208029 | O41: -122321724 | P41: -264410417 | Q41: -64112433 | R41: -58985345 | S41: -65929494 | T41: -95932080 | U41: -284959352 | V41: -182200793 | W41: -75242005 | X41: -98482407 | Y41: -110836619 | Z41: -466761824 | AB41: -57978637
A42: Proceeds from sale of PPE | D42: 70000 | E42: 41972 | F42: =SUM(B42:E42) -> 111972 | H42: 18268907 | I42: -57752 | J42: 988219 | K42: 19199374 | L42: 1285472 | M42: 1144264 | N42: 1144133 | O42: -5606 | P42: 3568263 | T42: 15007 | U42: 15007 | AB42: 214788628
A43: Payments for acquisition of intangible assets | D43: -1226195 | E43: -1231770 | F43: =SUM(B43:E43) -> -2457965 | J43: -2531617 | K43: -2531617 | N43: -607825 | O43: -3349727 | P43: -3957552 | Q43: -210867 | R43: -1010970 | S43: -182910 | T43: -4783982 | U43: -6188729 | V43: -39814 | W43: -1040 | X43: -181 | Y43: 41035 | AB43: -1070495
A44: Payments for acquisition of financial securities | O44: -48905131 | P44: -48905131 | Q44: -156483911 | R44: 0 | S44: 139078943 | T44: -581557273 | U44: -598962241
A45: Proceeds from financial securities | O45: 78643313 | P45: 78643313 | R45: 305996979 | S45: 86382076 | T45: 360389146 | U45: 752768201
A46: Proceeds from sale of other investments | B46: 7443 | C46: -7443 | AB46: 4942571
A47: Change in long-term notes receivable | B47: 3500000 | C47: -4032726 | D47: 532726 | E47: 3300000 | F47: =SUM(B47:E47) -> 3300000 | AB47: 16500000
A48: Net cash from / (used in) investing activities | B48: =SUM(B41:B47) -> -6541553 | C48: =SUM(C41:C47) -> -22454785 | D48: =SUM(D41:D47) -> -16714607 | E48: =SUM(E41:E47) -> -18663795 | F48: =SUM(F41:F47) -> -64374740 | G48: =SUM(G41:G47) -> -29707526 | H48: =SUM(H41:H47) -> 2240789 | I48: =SUM(I41:I47) -> -9668118 | ... Z48: =SUM(Z41:Z47) -> -466761824 | AB48: =SUM(AB41:AB47) -> 177182067
A49: Cash Flow from Financing Activities
A50: Payments of long-term loans | B50: -4842794 | C50: 2953019 | D50: -65257 | E50: -4753327 | F50: =SUM(B50:E50) -> -6708359 | G50: -99304 | H50: -5627381 | I50: -5640912 | J50: -10009376 | K50: -21376973 | L50: -9275829 | M50: -9534460 | N50: -9458864 | O50: -9475379 | P50: -37744532 | Q50: -9473877 | R50: 0 | S50: -820362 | T50: -181390 | U50: -10475629 | V50: -342476 | W50: 0 | X50: -1529 | Y50: 0 | Z50: -344005 | AB50: -18021421
A51: Payments of lease liabilities | B51: -1675093 | C51: -3357259 | D51: -4737168 | E51: -331208 | F51: =SUM(B51:E51) -> -10100728 | G51: -2128485 | H51: -353562 | I51: -5706552 | J51: -6954144 | K51: -15142743 | L51: -3601442 | M51: -5169613 | N51: -6761488 | O51: -5428582 | P51: -20961125 | Q51: -5916483 | R51: -9805061 | S51: 4720339 | T51: -13306742 | U51: -24307947 | V51: -10175517 | W51: -10449542 | X51: -13925600 | Y51: -9702301 | Z51: -44252960 | AB51: 2283156
A52: Payments of finance cost on lease contract | L52: -846785 | M52: 846785
A53: Payments for acquisition of treasury shares | M53: -25388998 | N53: 0 | O53: 0 | P53: -25388998
A54: Net proceeds from / (paid to) banks credit facilities | C54: 148752760 | D54: 15817129 | E54: -57800638 | F54: =SUM(B54:E54) -> 106769251 | G54: 81864493 | H54: 152871156 | I54: 48652562 | J54: 139934283 | K54: 423322494 | L54: 148029078 | M54: 136029551 | N54: 8474773 | O54: -152321276 | P54: 140212126 | Q54: -188950920 | R54: 45887949 | S54: 145991583 | T54: -471929548 | U54: -469000936 | V54: 483590732 | W54: 482125464 | X54: -298937833 | Y54: 2272455 | Z54: 669050818 | AB54: -37684668
A55: Proceeds from restricted time deposits | L55: 30000000 | M55: -30000000 | O55: 30000000 | P55: 30000000 | AB55: -16957202
A56: Payments / proceeds from hedge contracts | E56: 30431181 | F56: =SUM(B56:E56) -> 30431181 | J56: -104213713 | K56: -104213713
A57: Net cash from / (used in) financing activities | B57: =SUM(B50:B56) -> -6517887 | C57: =SUM(C50:C56) -> 148348520 | D57: =SUM(D50:D56) -> 11014704 | E57: =SUM(E50:E56) -> -32453992 | F57: =SUM(B57:E57) -> 120391345 | G57: =SUM(G50:G56) -> 79636704 | H57: =SUM(H50:H56) -> 146890213 | I57: =SUM(I50:I56) -> 37305098 | J57: =SUM(J50:J56) -> 18757050 | K57: =SUM(K50:K56) -> 282589065 | L57: =SUM(L50:L56) -> 164305022 | M57: =SUM(M50:M56) -> 66783265 | N57: =SUM(N50:N56) -> -7745579 | ... Z57: =SUM(Z50:Z56) -> 624453853 | AB57: =SUM(AB50:AB56) -> -70380135
A58: Net change in cash and cash equivalents | B58: =B39+B48+B57 -> 8466067 | C58: =C39+C48+C57 -> 27858301 | D58: =D39+D48+D57 -> -10339174 | E58: =E39+E48+E57 -> 25302020 | F58: =SUM(B58:E58) -> 51287214 | G58: =G39+G48+G57 -> 118915557 | H58: =H39+H48+H57 -> -11031312 | I58: =I39+I48+I57 -> 167364858 | J58: =J39+J48+J57 -> 45598170 | K58: =K39+K48+K57 -> 320847273 | L58: =L39+L48+L57 -> -139995560 | M58: =M39+M48+M57 -> -46057924 | N58: =N39+N48+N57 -> 71387396 | ... Z58: =Z39+Z48+Z57 -> -38283569 | AB58: =AB39+AB48+AB57 -> 459456186
A59: Cash and cash equivalents at the beginning of the period | B59: -597732765 | C59: 119446611 | D59: 119446611 | E59: 119446611 | F59: =SUM(B59:E59) -> -239392932 | G59: 132116247 | H59: 132116247 | I59: 132116247 | J59: 132116247 | K59: 132116247 | L59: 467963520 | M59: 467963520 | N59: 383008248 | O59: 467963520 | P59: 467963520 | Q59: 456269505 | R59: 456269505 | S59: 456269505 | T59: 456269505 | U59: 456269505 | V59: 352233706 | W59: 352233706 | X59: 352233706 | Y59: 352233706 | Z59: 352233706 | AB59: -1057188951
A60: Change in restricted time deposits | E60: -45000000 | F60: =SUM(B60:E60) -> -45000000 | H60: -30000000 | I60: -27000000 | J60: 15000000 | K60: 15000000 | L60: 30000000 | M60: 30000000 | N60: 30000000 | Q60: -472200 | V60: -505800 | W60: -496000 | X60: -478700 | Y60: -1697640 | Z60: -1697640
A61: Cash and cash equivalents at the end of the period | B61: =B59+B58+B60 -> -589266698 | C61: =C59+C58+C60 -> 147304912 | D61: =D59+D58+D60 -> 109107437 | E61: =E59+E58+E60 -> 99748631 | F61: =SUM(B61:E61) -> -233105718 | G61: =G59+G58+G60 -> 251031804 | H61: =H59+H58+H60 -> 91084935 | I61: =I59+I58+I60 -> 272481105 | J61: =J59+J58+J60 -> 192714417 | K61: =K59+K58+K60 -> 467963520 | L61: =L59+L58+L60 -> 357967960 | M61: =M59+M58+M60 -> 451905596 | N61: =N59+N58+N60 -> 484395644 | ... Z61: =Z59+Z58+Z60 -> 312252497 | AB61: =AB59+AB58+AB60 -> -597732765

Sheet Ratio Analysis
A1: LECICO EGYPT — Financial Ratio Analysis | All Quarters 2021–2025
B2: 2021 | G2: 2022 | L2: 2023 | Q2: 2024 | V2: 2025 | AB2: 2020
A3: Item | B3: Q1-2021 | C3: Q2-2021 | D3: Q3-2021 | E3: Q4-2021 | F3: FY-2021 | G3: Q1-2022 | H3: Q2-2022 | I3: Q3-2022 | J3: Q4-2022 | K3: FY-2022 | L3: Q1-2023 | M3: Q2-2023 | N3: Q3-2023 | O3: Q4-2023 | P3: FY-2023 | Q3: Q1-2024 | R3: Q2-2024 | S3: Q3-2024 | T3: Q4-2024 | U3: FY-2024 | V3: Q1-2025 | W3: Q2-2025 | X3: Q3-2025 | Y3: Q4-2025 | Z3: FY-2025 | AB3: FY-2020
A5: I. PROFITABILITY RATIOS
A6: Gross Margin | B6: ='Income Statement'!C8/'Income Statement'!C6 -> 0.16617922 | C6: ='Income Statement'!D8/'Income Statement'!D6 -> 0.17636084 | D6: ='Income Statement'!E8/'Income Statement'!E6 -> 0.1832087 | E6: ='Income Statement'!F8/'Income Statement'!F6 -> 0.20219846 | F6: ='Income Statement'!G8/'Income Statement'!G6 -> 0.18290858 | G6: ='Income Statement'!H8/'Income Statement'!H6 -> 0.20432135 | H6: ='Income Statement'!I8/'Income Statement'!I6 -> 0.18767416 | I6: ='Income Statement'!J8/'Income Statement'!J6 -> 0.13258603 | ... Z6: ='Income Statement'!AA8/'Income Statement'!AA6 -> 0.22872483 | AB6: ='Income Statement'!AB8/'Income Statement'!AB6 -> 0.11150668
A7: EBIT Margin | B7: ='Income Statement'!C16/'Income Statement'!C6 -> 0.017268414 | C7: ='Income Statement'!D16/'Income Statement'!D6 -> 0.0047995623 | D7: ='Income Statement'!E16/'Income Statement'!E6 -> 0.013651111 | E7: ='Income Statement'!F16/'Income Statement'!F6 -> 0.037511523 | F7: ='Income Statement'!G16/'Income Statement'!G6 -> 0.018899623 | G7: ='Income Statement'!H16/'Income Statement'!H6 -> 0.041024035 | H7: ='Income Statement'!I16/'Income Statement'!I6 -> -0.051318378 | I7: ='Income Statement'!J16/'Income Statement'!J6 -> -0.11044692 | ... Z7: ='Income Statement'!AA16/'Income Statement'!AA6 -> 0.095156259 | AB7: ='Income Statement'!AB16/'Income Statement'!AB6 -> -0.064447451
A8: Net Profit Margin | B8: ='Income Statement'!C24/'Income Statement'!C6 -> -0.023574644 | C8: ='Income Statement'!D24/'Income Statement'!D6 -> -0.0066444245 | D8: ='Income Statement'!E24/'Income Statement'!E6 -> -0.0071664336 | E8: ='Income Statement'!F24/'Income Statement'!F6 -> -0.00011531035 | F8: ='Income Statement'!G24/'Income Statement'!G6 -> -0.0088322046 | G8: ='Income Statement'!H24/'Income Statement'!H6 -> 0.044709892 | H8: ='Income Statement'!I24/'Income Statement'!I6 -> -0.079915979 | I8: ='Income Statement'!J24/'Income Statement'!J6 -> -0.0061823537 | ... Z8: ='Income Statement'!AA24/'Income Statement'!AA6 -> 0.033227575 | AB8: ='Income Statement'!AB24/'Income Statement'!AB6 -> -0.10821498
A9: Effective Tax Rate | B9: =IFERROR(IF(OR('Income Statement'!D21=0,ABS('Income Statement'!D22/'Income Statement'!D21)>2),NA(),'Income Statement'!D22/'Income Statement'!D21),NA()) -> -1.8471522 | C9: =IFERROR(IF(OR('Income Statement'!E21=0,ABS('Income Statement'!E22/'Income Statement'!E21)>2),NA(),'Income Statement'!E22/'Income Statement'!E21),NA()) -> -1.9001116 | D9: =IFERROR(IF(OR('Income Statement'!F21=0,ABS('Income Statement'!F22/'Income Statement'!F21)>2),NA(),'Income Statement'!F22/'Income Statement'!F21),NA()) -> -1.0034651 | E9: =IFERROR(IF(OR('Income Statement'!G21=0,ABS('Income Statement'!G22/'Income Statement'!G21)>2),NA(),'Income Statement'!G22/'Income Statement'!G21),NA()) -> -1.7091653 | F9: =IFERROR(IF(OR('Income Statement'!H21=0,ABS('Income Statement'!H22/'Income Statement'!H21)>2),NA(),'Income Statement'!H22/'Income Statement'!H21),NA()) -> -0.36561143 | G9: =IFERROR(IF(OR('Income Statement'!I21=0,ABS('Income Statement'!I22/'Income Statement'!I21)>2),NA(),'Income Statement'!I22/'Income Statement'!I21),NA()) -> 0.45430674 | H9: =IFERROR(IF(OR('Income Statement'!J21=0,ABS('Income Statement'!J22/'Income Statement'!J21)>2),NA(),'Income Statement'!J22/'Income Statement'!J21),NA()) -> -1.6490525 | I9: =IFERROR(IF(OR('Income Statement'!K21=0,ABS('Income Statement'!K22/'Income Statement'!K21)>2),NA(),'Income Statement'!K22/'Income Statement'!K21),NA()) -> -0.23419562 | ... Y9: =IFERROR(IF(OR('Income Statement'!AA21=0,ABS('Income Statement'!AA22/'Income Statement'!AA21)>2),NA(),'Income Statement'!AA22/'Income Statement'!AA21),NA()) -> -0.43834894 | AB9: =IFERROR(IF(OR('Income Statement'!AB21=0,ABS('Income Statement'!AB22/'Income Statement'!AB21)>2),NA(),'Income Statement'!AB22/'Income Statement'!AB21),NA()) -> 0.12351216
A10: Return on Assets (ROA) | B10: ='Income Statement'!C24/'Balance Sheet'!C19 -> -0.0042179015 | C10: ='Income Statement'!D24/'Balance Sheet'!D19 -> -0.0012058749 | D10: ='Income Statement'!E24/'Balance Sheet'!E19 -> -0.0013899395 | E10: ='Income Statement'!F24/'Balance Sheet'!F19 -> -2.4446238e-05 | F10: ='Income Statement'!G24/'Balance Sheet'!F19 -> -0.0068136986 | G10: ='Income Statement'!H24/'Balance Sheet'!G19 -> 0.0090245766 | H10: ='Income Statement'!I24/'Balance Sheet'!H19 -> -0.014232859 | I10: ='Income Statement'!J24/'Balance Sheet'!I19 -> -0.0012399071 | J10: ='Income Statement'!K24/'Balance Sheet'!J19 -> 0.009047507 | K10: ='Income Statement'!L24/'Balance Sheet'!J19 -> 0.0027109229 | L10: ='Income Statement'!M24/'Balance Sheet'!K19 -> 0.018056153 | M10: ='Income Statement'!N24/'Balance Sheet'!L19 -> 0.032512586 | N10: ='Income Statement'!O24/'Balance Sheet'!M19 -> 0.016211106 | O10: ='Income Statement'!P24/'Balance Sheet'!N19 -> 0.02202437 | P10: ='Income Statement'!Q24/'Balance Sheet'!N19 -> 0.086688078 | Q10: ='Income Statement'!R24/'Balance Sheet'!O19 -> 0.076891086 | R10: ='Income Statement'!S24/'Balance Sheet'!P19 -> 0.024731954 | S10: ='Income Statement'!T24/'Balance Sheet'!Q19 -> 0.028701912 | T10: ='Income Statement'!U24/'Balance Sheet'!R19 -> 0.0049671329 | U10: ='Income Statement'!V24/'Balance Sheet'!R19 -> 0.11867112 | V10: ='Income Statement'!W24/'Balance Sheet'!S19 -> 0.011478369 | W10: ='Income Statement'!X24/'Balance Sheet'!T19 -> 0.0064993556 | X10: ='Income Statement'!Y24/'Balance Sheet'!U19 -> 0.012091006 | Y10: ='Income Statement'!Z24/'Balance Sheet'!V19 -> 0.00092922366 | Z10: ='Income Statement'!AA24/'Balance Sheet'!V19 -> 0.030373212 | AB10: =NA() -> #N/A
A11: Return on Equity (ROE) | B11: ='Income Statement'!C27/'Balance Sheet'!C27 -> -0.011036894 | C11: ='Income Statement'!D27/'Balance Sheet'!D27 -> -0.0045037666 | D11: ='Income Statement'!E27/'Balance Sheet'!E27 -> -0.0057366338 | E11: ='Income Statement'!F27/'Balance Sheet'!F27 -> -0.0027296233 | F11: ='Income Statement'!G27/'Balance Sheet'!F27 -> -0.02411066 | G11: ='Income Statement'!H27/'Balance Sheet'!G27 -> 0.018689092 | H11: ='Income Statement'!I27/'Balance Sheet'!H27 -> -0.033391665 | I11: ='Income Statement'!J27/'Balance Sheet'!I27 -> -0.0053546362 | J11: ='Income Statement'!K27/'Balance Sheet'!J27 -> 0.020461172 | K11: ='Income Statement'!L27/'Balance Sheet'!J27 -> -0.0017305975 | L11: ='Income Statement'!M27/'Balance Sheet'!K27 -> 0.047653892 | M11: ='Income Statement'!N27/'Balance Sheet'!L27 -> 0.083681571 | N11: ='Income Statement'!O27/'Balance Sheet'!M27 -> 0.037940205 | O11: ='Income Statement'!P27/'Balance Sheet'!N27 -> 0.050678625 | P11: ='Income Statement'!Q27/'Balance Sheet'!N27 -> 0.20420163 | Q11: ='Income Statement'!R27/'Balance Sheet'!O27 -> 0.17389548 | R11: ='Income Statement'!S27/'Balance Sheet'!P27 -> 0.051710244 | S11: ='Income Statement'!T27/'Balance Sheet'!Q27 -> 0.061832438 | T11: ='Income Statement'!U27/'Balance Sheet'!R27 -> 0.0092649587 | U11: ='Income Statement'!V27/'Balance Sheet'!R27 -> 0.23840163 | V11: ='Income Statement'!W27/'Balance Sheet'!S27 -> 0.024130014 | W11: ='Income Statement'!X27/'Balance Sheet'!T27 -> 0.013659916 | X11: ='Income Statement'!Y27/'Balance Sheet'!U27 -> 0.024433812 | Y11: ='Income Statement'!Z27/'Balance Sheet'!V27 -> 0.00036809468 | Z11: ='Income Statement'!AA27/'Balance Sheet'!V27 -> 0.061359018 | AB11: =NA() -> #N/A
A12: II. LIQUIDITY RATIOS
A13: Current Ratio | B13: ='Balance Sheet'!C18/'Balance Sheet'!C44 -> 0.97739053 | C13: ='Balance Sheet'!D18/'Balance Sheet'!D44 -> 0.99826275 | D13: ='Balance Sheet'!E18/'Balance Sheet'!E44 -> 1.1097515 | E13: ='Balance Sheet'!F18/'Balance Sheet'!F44 -> 1.1375598 | F13: ='Balance Sheet'!F18/'Balance Sheet'!F44 -> 1.1375598 | G13: ='Balance Sheet'!G18/'Balance Sheet'!G44 -> 1.1591272 | H13: ='Balance Sheet'!H18/'Balance Sheet'!H44 -> 1.1569525 | I13: ='Balance Sheet'!I18/'Balance Sheet'!I44 -> 1.1478823 | J13: ='Balance Sheet'!J18/'Balance Sheet'!J44 -> 1.1591795 | K13: ='Balance Sheet'!J18/'Balance Sheet'!J44 -> 1.1591795 | L13: ='Balance Sheet'!K18/'Balance Sheet'!K44 -> 1.1491139 | M13: ='Balance Sheet'!L18/'Balance Sheet'!L44 -> 1.2013085 | N13: ='Balance Sheet'!M18/'Balance Sheet'!M44 -> 1.2110844 | O13: ='Balance Sheet'!N18/'Balance Sheet'!N44 -> 1.2267967 | P13: ='Balance Sheet'!N18/'Balance Sheet'!N44 -> 1.2267967 | Q13: ='Balance Sheet'!O18/'Balance Sheet'!O44 -> 1.3752677 | R13: ='Balance Sheet'!P18/'Balance Sheet'!P44 -> 1.4159141 | S13: ='Balance Sheet'!Q18/'Balance Sheet'!Q44 -> 1.4602208 | T13: ='Balance Sheet'!R18/'Balance Sheet'!R44 -> 1.4928713 | U13: ='Balance Sheet'!R18/'Balance Sheet'!R44 -> 1.4928713 | V13: ='Balance Sheet'!S18/'Balance Sheet'!S44 -> 1.438429 | W13: ='Balance Sheet'!T18/'Balance Sheet'!T44 -> 1.3942508 | X13: ='Balance Sheet'!U18/'Balance Sheet'!U44 -> 1.3887239 | Y13: ='Balance Sheet'!V18/'Balance Sheet'!V44 -> 1.3648887 | Z13: ='Balance Sheet'!V18/'Balance Sheet'!V44 -> 1.3648887 | AB13: =NA() -> #N/A
A14: Quick Ratio | B14: =('Balance Sheet'!C18-'Balance Sheet'!C14)/'Balance Sheet'!C44 -> 0.48006816 | C14: =('Balance Sheet'!D18-'Balance Sheet'!D14)/'Balance Sheet'!D44 -> 0.48511415 | D14: =('Balance Sheet'!E18-'Balance Sheet'!E14)/'Balance Sheet'!E44 -> 0.52546678 | E14: =('Balance Sheet'!F18-'Balance Sheet'!F14)/'Balance Sheet'!F44 -> 0.52785857 | F14: =('Balance Sheet'!F18-'Balance Sheet'!F14)/'Balance Sheet'!F44 -> 0.52785857 | G14: =('Balance Sheet'!G18-'Balance Sheet'!G14)/'Balance Sheet'!G44 -> 0.5885993 | H14: =('Balance Sheet'!H18-'Balance Sheet'!H14)/'Balance Sheet'!H44 -> 0.5792795 | I14: =('Balance Sheet'!I18-'Balance Sheet'!I14)/'Balance Sheet'!I44 -> 0.6426254 | J14: =('Balance Sheet'!J18-'Balance Sheet'!J14)/'Balance Sheet'!J44 -> 0.6249191 | K14: =('Balance Sheet'!J18-'Balance Sheet'!J14)/'Balance Sheet'!J44 -> 0.6249191 | L14: =('Balance Sheet'!K18-'Balance Sheet'!K14)/'Balance Sheet'!K44 -> 0.54882495 | M14: =('Balance Sheet'!L18-'Balance Sheet'!L14)/'Balance Sheet'!L44 -> 0.54885053 | N14: =('Balance Sheet'!M18-'Balance Sheet'!M14)/'Balance Sheet'!M44 -> 0.56261815 | O14: =('Balance Sheet'!N18-'Balance Sheet'!N14)/'Balance Sheet'!N44 -> 0.6208146 | P14: =('Balance Sheet'!N18-'Balance Sheet'!N14)/'Balance Sheet'!N44 -> 0.6208146 | Q14: =('Balance Sheet'!O18-'Balance Sheet'!O14)/'Balance Sheet'!O44 -> 0.74627952 | R14: =('Balance Sheet'!P18-'Balance Sheet'!P14)/'Balance Sheet'!P44 -> 0.68578625 | S14: =('Balance Sheet'!Q18-'Balance Sheet'!Q14)/'Balance Sheet'!Q44 -> 0.74573248 | T14: =('Balance Sheet'!R18-'Balance Sheet'!R14)/'Balance Sheet'!R44 -> 0.61789975 | U14: =('Balance Sheet'!R18-'Balance Sheet'!R14)/'Balance Sheet'!R44 -> 0.61789975 | V14: =('Balance Sheet'!S18-'Balance Sheet'!S14)/'Balance Sheet'!S44 -> 0.61719377 | W14: =('Balance Sheet'!T18-'Balance Sheet'!T14)/'Balance Sheet'!T44 -> 0.6176059 | X14: =('Balance Sheet'!U18-'Balance Sheet'!U14)/'Balance Sheet'!U44 -> 0.58250167 | Y14: =('Balance Sheet'!V18-'Balance Sheet'!V14)/'Balance Sheet'!V44 -> 0.55490275 | Z14: =('Balance Sheet'!V18-'Balance Sheet'!V14)/'Balance Sheet'!V44 -> 0.55490275 | AB14: =NA() -> #N/A
A15: Cash Ratio | B15: ='Balance Sheet'!C17/'Balance Sheet'!C44 -> 0.088361781 | C15: ='Balance Sheet'!D17/'Balance Sheet'!D44 -> 0.082806597 | D15: ='Balance Sheet'!E17/'Balance Sheet'!E44 -> 0.085184439 | E15: ='Balance Sheet'!F17/'Balance Sheet'!F44 -> 0.11058314 | F15: ='Balance Sheet'!F17/'Balance Sheet'!F44 -> 0.11058314 | G15: ='Balance Sheet'!G17/'Balance Sheet'!G44 -> 0.16506927 | H15: ='Balance Sheet'!H17/'Balance Sheet'!H44 -> 0.15091657 | I15: ='Balance Sheet'!I17/'Balance Sheet'!I44 -> 0.21618385 | J15: ='Balance Sheet'!J17/'Balance Sheet'!J44 -> 0.21486866 | K15: ='Balance Sheet'!J17/'Balance Sheet'!J44 -> 0.21486866 | L15: ='Balance Sheet'!K17/'Balance Sheet'!K44 -> 0.12717886 | M15: ='Balance Sheet'!L17/'Balance Sheet'!L44 -> 0.11294914 | N15: ='Balance Sheet'!M17/'Balance Sheet'!M44 -> 0.1177293 | O15: ='Balance Sheet'!N17/'Balance Sheet'!N44 -> 0.17313517 | P15: ='Balance Sheet'!N17/'Balance Sheet'!N44 -> 0.17313517 | Q15: ='Balance Sheet'!O17/'Balance Sheet'!O44 -> 0.24950428 | R15: ='Balance Sheet'!P17/'Balance Sheet'!P44 -> 0.16772638 | S15: ='Balance Sheet'!Q17/'Balance Sheet'!Q44 -> 0.20225855 | T15: ='Balance Sheet'!R17/'Balance Sheet'!R44 -> 0.12117651 | U15: ='Balance Sheet'!R17/'Balance Sheet'!R44 -> 0.12117651 | V15: ='Balance Sheet'!S17/'Balance Sheet'!S44 -> 0.11184782 | W15: ='Balance Sheet'!T17/'Balance Sheet'!T44 -> 0.10079594 | X15: ='Balance Sheet'!U17/'Balance Sheet'!U44 -> 0.099149397 | Y15: ='Balance Sheet'!V17/'Balance Sheet'!V44 -> 0.088287083 | Z15: ='Balance Sheet'!V17/'Balance Sheet'!V44 -> 0.088287083 | AB15: =NA() -> #N/A
A16: III. LEVERAGE RATIOS
A17: Debt-to-Equity | B17: ='Balance Sheet'!C45/'Balance Sheet'!C29 -> 1.1608442 | C17: ='Balance Sheet'!D45/'Balance Sheet'!D29 -> 1.2601438 | D17: ='Balance Sheet'!E45/'Balance Sheet'!E29 -> 1.2728504 | E17: ='Balance Sheet'!F45/'Balance Sheet'!F29 -> 1.2195507 | F17: ='Balance Sheet'!F45/'Balance Sheet'!F29 -> 1.2195507 | G17: ='Balance Sheet'!G45/'Balance Sheet'!G29 -> 1.3088586 | H17: ='Balance Sheet'!H45/'Balance Sheet'!H29 -> 1.1890722 | I17: ='Balance Sheet'!I45/'Balance Sheet'!I29 -> 1.3128613 | J17: ='Balance Sheet'!J45/'Balance Sheet'!J29 -> 1.4708539 | K17: ='Balance Sheet'!J45/'Balance Sheet'!J29 -> 1.4708539 | L17: ='Balance Sheet'!K45/'Balance Sheet'!K29 -> 1.6079129 | M17: ='Balance Sheet'!L45/'Balance Sheet'!L29 -> 1.5968875 | N17: ='Balance Sheet'!M45/'Balance Sheet'!M29 -> 1.5234395 | O17: ='Balance Sheet'!N45/'Balance Sheet'!N29 -> 1.4120082 | P17: ='Balance Sheet'!N45/'Balance Sheet'!N29 -> 1.4120082 | Q17: ='Balance Sheet'!O45/'Balance Sheet'!O29 -> 1.2271742 | R17: ='Balance Sheet'!P45/'Balance Sheet'!P29 -> 1.1677501 | S17: ='Balance Sheet'!Q45/'Balance Sheet'!Q29 -> 1.1390391 | T17: ='Balance Sheet'!R45/'Balance Sheet'!R29 -> 1.0088565 | U17: ='Balance Sheet'!R45/'Balance Sheet'!R29 -> 1.0088565 | V17: ='Balance Sheet'!S45/'Balance Sheet'!S29 -> 1.0471108 | W17: ='Balance Sheet'!T45/'Balance Sheet'!T29 -> 1.1174876 | X17: ='Balance Sheet'!U45/'Balance Sheet'!U29 -> 1.0872247 | Y17: ='Balance Sheet'!V45/'Balance Sheet'!V29 -> 1.0792589 | Z17: ='Balance Sheet'!V45/'Balance Sheet'!V29 -> 1.0792589 | AB17: =NA() -> #N/A
A18: Debt-to-Assets | B18: ='Balance Sheet'!C45/'Balance Sheet'!C19 -> 0.5372179 | C18: ='Balance Sheet'!D45/'Balance Sheet'!D19 -> 0.55755028 | D18: ='Balance Sheet'!E45/'Balance Sheet'!E19 -> 0.56002383 | E18: ='Balance Sheet'!F45/'Balance Sheet'!F19 -> 0.54945837 | F18: ='Balance Sheet'!F45/'Balance Sheet'!F19 -> 0.54945837 | G18: ='Balance Sheet'!G45/'Balance Sheet'!G19 -> 0.56688555 | H18: ='Balance Sheet'!H45/'Balance Sheet'!H19 -> 0.54318547 | I18: ='Balance Sheet'!I45/'Balance Sheet'!I19 -> 0.56763513 | J18: ='Balance Sheet'!J45/'Balance Sheet'!J19 -> 0.59528161 | K18: ='Balance Sheet'!J45/'Balance Sheet'!J19 -> 0.59528161 | L18: ='Balance Sheet'!K45/'Balance Sheet'!K19 -> 0.61655161 | M18: ='Balance Sheet'!L45/'Balance Sheet'!L19 -> 0.61492364 | N18: ='Balance Sheet'!M45/'Balance Sheet'!M19 -> 0.60371548 | O18: ='Balance Sheet'!N45/'Balance Sheet'!N19 -> 0.58540771 | P18: ='Balance Sheet'!N45/'Balance Sheet'!N19 -> 0.58540771 | Q18: ='Balance Sheet'!O45/'Balance Sheet'!O19 -> 0.55100055 | R18: ='Balance Sheet'!P45/'Balance Sheet'!P19 -> 0.53869222 | S18: ='Balance Sheet'!Q45/'Balance Sheet'!Q19 -> 0.53250036 | T18: ='Balance Sheet'!R45/'Balance Sheet'!R19 -> 0.50220437 | U18: ='Balance Sheet'!R45/'Balance Sheet'!R19 -> 0.50220437 | V18: ='Balance Sheet'!S45/'Balance Sheet'!S19 -> 0.51150665 | W18: ='Balance Sheet'!T45/'Balance Sheet'!T19 -> 0.52774222 | X18: ='Balance Sheet'!U45/'Balance Sheet'!U19 -> 0.5208949 | Y18: ='Balance Sheet'!V45/'Balance Sheet'!V19 -> 0.51905941 | Z18: ='Balance Sheet'!V45/'Balance Sheet'!V19 -> 0.51905941 | AB18: =NA() -> #N/A
A19: Equity Ratio | B19: ='Balance Sheet'!C29/'Balance Sheet'!C19 -> 0.4627821 | C19: ='Balance Sheet'!D29/'Balance Sheet'!D19 -> 0.44244972 | D19: ='Balance Sheet'!E29/'Balance Sheet'!E19 -> 0.43997617 | E19: ='Balance Sheet'!F29/'Balance Sheet'!F19 -> 0.45054163 | F19: ='Balance Sheet'!F29/'Balance Sheet'!F19 -> 0.45054163 | G19: ='Balance Sheet'!G29/'Balance Sheet'!G19 -> 0.43311445 | H19: ='Balance Sheet'!H29/'Balance Sheet'!H19 -> 0.45681453 | I19: ='Balance Sheet'!I29/'Balance Sheet'!I19 -> 0.43236487 | J19: ='Balance Sheet'!J29/'Balance Sheet'!J19 -> 0.40471839 | K19: ='Balance Sheet'!J29/'Balance Sheet'!J19 -> 0.40471839 | L19: ='Balance Sheet'!K29/'Balance Sheet'!K19 -> 0.38344839 | M19: ='Balance Sheet'!L29/'Balance Sheet'!L19 -> 0.38507636 | N19: ='Balance Sheet'!M29/'Balance Sheet'!M19 -> 0.39628452 | O19: ='Balance Sheet'!N29/'Balance Sheet'!N19 -> 0.41459229 | P19: ='Balance Sheet'!N29/'Balance Sheet'!N19 -> 0.41459229 | Q19: ='Balance Sheet'!O29/'Balance Sheet'!O19 -> 0.44899945 | R19: ='Balance Sheet'!P29/'Balance Sheet'!P19 -> 0.46130778 | S19: ='Balance Sheet'!Q29/'Balance Sheet'!Q19 -> 0.46749964 | T19: ='Balance Sheet'!R29/'Balance Sheet'!R19 -> 0.49779563 | U19: ='Balance Sheet'!R29/'Balance Sheet'!R19 -> 0.49779563 | V19: ='Balance Sheet'!S29/'Balance Sheet'!S19 -> 0.48849335 | W19: ='Balance Sheet'!T29/'Balance Sheet'!T19 -> 0.47225778 | X19: ='Balance Sheet'!U29/'Balance Sheet'!U19 -> 0.4791051 | Y19: ='Balance Sheet'!V29/'Balance Sheet'!V19 -> 0.48094059 | Z19: ='Balance Sheet'!V29/'Balance Sheet'!V19 -> 0.48094059 | AB19: =NA() -> #N/A
A20: IV. EFFICIENCY RATIOS
A21: Asset Turnover | B21: ='Income Statement'!C6/'Balance Sheet'!C19 -> 0.17891687 | C21: ='Income Statement'!D6/'Balance Sheet'!D19 -> 0.18148673 | D21: ='Income Statement'!E6/'Balance Sheet'!E19 -> 0.19395135 | E21: ='Income Statement'!F6/'Balance Sheet'!F19 -> 0.21200385 | F21: ='Income Statement'!G6/'Balance Sheet'!F19 -> 0.77146069 | G21: ='Income Statement'!H6/'Balance Sheet'!G19 -> 0.20184743 | H21: ='Income Statement'!I6/'Balance Sheet'!H19 -> 0.17809778 | I21: ='Income Statement'!J6/'Balance Sheet'!I19 -> 0.20055584 | J21: ='Income Statement'!K6/'Balance Sheet'!J19 -> 0.20240021 | K21: ='Income Statement'!L6/'Balance Sheet'!J19 -> 0.69721789 | L21: ='Income Statement'!M6/'Balance Sheet'!K19 -> 0.24260542 | M21: ='Income Statement'!N6/'Balance Sheet'!L19 -> 0.22055247 | N21: ='Income Statement'!O6/'Balance Sheet'!M19 -> 0.22552962 | O21: ='Income Statement'!P6/'Balance Sheet'!N19 -> 0.2241821 | P21: ='Income Statement'!Q6/'Balance Sheet'!N19 -> 0.88772895 | Q21: ='Income Statement'!R6/'Balance Sheet'!O19 -> 0.21955363 | R21: ='Income Statement'!S6/'Balance Sheet'!P19 -> 0.23742624 | S21: ='Income Statement'!T6/'Balance Sheet'!Q19 -> 0.23668554 | T21: ='Income Statement'!U6/'Balance Sheet'!R19 -> 0.23034648 | U21: ='Income Statement'!V6/'Balance Sheet'!R19 -> 0.8576692 | V21: ='Income Statement'!W6/'Balance Sheet'!S19 -> 0.2089796 | W21: ='Income Statement'!X6/'Balance Sheet'!T19 -> 0.22125331 | X21: ='Income Statement'!Y6/'Balance Sheet'!U19 -> 0.25437687 | Y21: ='Income Statement'!Z6/'Balance Sheet'!V19 -> 0.24143235 | Z21: ='Income Statement'!AA6/'Balance Sheet'!V19 -> 0.91409656 | AB21: =NA() -> #N/A
A22: Inventory Turnover | B22: =-'Income Statement'!C7/'Balance Sheet'!C14 -> 0.57518231 | C22: =-'Income Statement'!D7/'Balance Sheet'!D14 -> 0.54266359 | D22: =-'Income Statement'!E7/'Balance Sheet'!E14 -> 0.55685623 | E22: =-'Income Statement'!F7/'Balance Sheet'!F14 -> 0.59320603 | F22: =-'Income Statement'!G7/'Balance Sheet'!F14 -> 2.2108099 | G22: =-'Income Statement'!H7/'Balance Sheet'!G14 -> 0.57976182 | H22: =-'Income Statement'!I7/'Balance Sheet'!H14 -> 0.53857996 | I22: =-'Income Statement'!J7/'Balance Sheet'!I14 -> 0.70115453 | J22: =-'Income Statement'!K7/'Balance Sheet'!J14 -> 0.60830594 | K22: =-'Income Statement'!L7/'Balance Sheet'!J14 -> 2.1606375 | L22: =-'Income Statement'!M7/'Balance Sheet'!K14 -> 0.46269922 | M22: =-'Income Statement'!N7/'Balance Sheet'!L14 -> 0.41454189 | N22: =-'Income Statement'!O7/'Balance Sheet'!M14 -> 0.48759702 | O22: =-'Income Statement'!P7/'Balance Sheet'!N14 -> 0.55612975 | P22: =-'Income Statement'!Q7/'Balance Sheet'!N14 -> 2.0093111 | Q22: =-'Income Statement'!R7/'Balance Sheet'!O14 -> 0.52321556 | R22: =-'Income Statement'!S7/'Balance Sheet'!P14 -> 0.50940207 | S22: =-'Income Statement'!T7/'Balance Sheet'!Q14 -> 0.59174402 | T22: =-'Income Statement'!U7/'Balance Sheet'!R14 -> 0.5282111 | U22: =-'Income Statement'!V7/'Balance Sheet'!R14 -> 1.8752627 | V22: =-'Income Statement'!W7/'Balance Sheet'!S14 -> 0.48090785 | W22: =-'Income Statement'!X7/'Balance Sheet'!T14 -> 0.52382999 | X22: =-'Income Statement'!Y7/'Balance Sheet'!U14 -> 0.58180066 | Y22: =-'Income Statement'!Z7/'Balance Sheet'!V14 -> 0.58366935 | Z22: =-'Income Statement'!AA7/'Balance Sheet'!V14 -> 2.0896205 | AB22: =NA() -> #N/A
A23: Days Inventory Outstanding (DIO) | B23: =IFERROR(365/B22,NA()) -> 634.58141 | C23: =IFERROR(365/C22,NA()) -> 672.60824 | D23: =IFERROR(365/D22,NA()) -> 655.46542 | E23: =IFERROR(365/E22,NA()) -> 615.30056 | F23: =IFERROR(365/F22,NA()) -> 165.09787 | G23: =IFERROR(365/G22,NA()) -> 629.56888 | H23: =IFERROR(365/H22,NA()) -> 677.7081 | I23: =IFERROR(365/I22,NA()) -> 520.56998 | ... Z23: =IFERROR(365/Z22,NA()) -> 174.67286 | AB23: =NA() -> #N/A
A24: Receivables Turnover | B24: ='Income Statement'!C6/'Balance Sheet'!C15 -> 0.87581054 | C24: ='Income Statement'!D6/'Balance Sheet'!D15 -> 0.84038571 | D24: ='Income Statement'!E6/'Balance Sheet'!E15 -> 0.90474304 | E24: ='Income Statement'!F6/'Balance Sheet'!F15 -> 1.086438 | F24: ='Income Statement'!G6/'Balance Sheet'!F15 -> 3.9534387 | G24: ='Income Statement'!H6/'Balance Sheet'!G15 -> 0.98153225 | H24: ='Income Statement'!I6/'Balance Sheet'!H15 -> 0.89410822 | I24: ='Income Statement'!J6/'Balance Sheet'!I15 -> 0.95772328 | J24: ='Income Statement'!K6/'Balance Sheet'!J15 -> 1.0000711 | K24: ='Income Statement'!L6/'Balance Sheet'!J15 -> 3.4449936 | L24: ='Income Statement'!M6/'Balance Sheet'!K15 -> 1.1190128 | M24: ='Income Statement'!N6/'Balance Sheet'!L15 -> 0.98667832 | N24: ='Income Statement'!O6/'Balance Sheet'!M15 -> 1.0076938 | O24: ='Income Statement'!P6/'Balance Sheet'!N15 -> 1.0366342 | P24: ='Income Statement'!Q6/'Balance Sheet'!N15 -> 4.1049229 | Q24: ='Income Statement'!R6/'Balance Sheet'!O15 -> 0.96535686 | R24: ='Income Statement'!S6/'Balance Sheet'!P15 -> 1.0190732 | S24: ='Income Statement'!T6/'Balance Sheet'!Q15 -> 1.1951415 | T24: ='Income Statement'!U6/'Balance Sheet'!R15 -> 1.2359741 | U24: ='Income Statement'!V6/'Balance Sheet'!R15 -> 4.6020104 | V24: ='Income Statement'!W6/'Balance Sheet'!S15 -> 1.0568647 | W24: ='Income Statement'!X6/'Balance Sheet'!T15 -> 1.0346119 | X24: ='Income Statement'!Y6/'Balance Sheet'!U15 -> 1.2719803 | Y24: ='Income Statement'!Z6/'Balance Sheet'!V15 -> 1.242166 | Z24: ='Income Statement'!AA6/'Balance Sheet'!V15 -> 4.7030139 | AB24: =NA() -> #N/A
A25: Days Sales Outstanding (DSO) | B25: =IFERROR(365/B24,NA()) -> 416.7568 | C25: =IFERROR(365/C24,NA()) -> 434.32438 | D25: =IFERROR(365/D24,NA()) -> 403.42946 | E25: =IFERROR(365/E24,NA()) -> 335.96027 | F25: =IFERROR(365/F24,NA()) -> 92.32469 | G25: =IFERROR(365/G24,NA()) -> 371.86756 | H25: =IFERROR(365/H24,NA()) -> 408.22799 | I25: =IFERROR(365/I24,NA()) -> 381.11217 | ... Z25: =IFERROR(365/Z24,NA()) -> 77.609808 | AB25: =NA() -> #N/A
A26: Payables Turnover | B26: =-'Income Statement'!C7/'Balance Sheet'!C42 -> 0.54479091 | C26: =-'Income Statement'!D7/'Balance Sheet'!D42 -> 0.56641986 | D26: =-'Income Statement'!E7/'Balance Sheet'!E42 -> 0.73340419 | E26: =-'Income Statement'!F7/'Balance Sheet'!F42 -> 0.85982251 | F26: =-'Income Statement'!G7/'Balance Sheet'!F42 -> 3.2044584 | G26: =-'Income Statement'!H7/'Balance Sheet'!G42 -> 0.71862087 | H26: =-'Income Statement'!I7/'Balance Sheet'!H42 -> 0.77055713 | I26: =-'Income Statement'!J7/'Balance Sheet'!I42 -> 0.81364145 | J26: =-'Income Statement'!K7/'Balance Sheet'!J42 -> 0.80711614 | K26: =-'Income Statement'!L7/'Balance Sheet'!J42 -> 2.8667901 | L26: =-'Income Statement'!M7/'Balance Sheet'!K42 -> 0.74129046 | M26: =-'Income Statement'!N7/'Balance Sheet'!L42 -> 0.76312285 | N26: =-'Income Statement'!O7/'Balance Sheet'!M42 -> 0.86190175 | O26: =-'Income Statement'!P7/'Balance Sheet'!N42 -> 0.93068105 | P26: =-'Income Statement'!Q7/'Balance Sheet'!N42 -> 3.3625746 | Q26: =-'Income Statement'!R7/'Balance Sheet'!O42 -> 0.75099142 | R26: =-'Income Statement'!S7/'Balance Sheet'!P42 -> 0.79953474 | S26: =-'Income Statement'!T7/'Balance Sheet'!Q42 -> 0.92561896 | T26: =-'Income Statement'!U7/'Balance Sheet'!R42 -> 0.88888661 | U26: =-'Income Statement'!V7/'Balance Sheet'!R42 -> 3.1557381 | V26: =-'Income Statement'!W7/'Balance Sheet'!S42 -> 1.010532 | W26: =-'Income Statement'!X7/'Balance Sheet'!T42 -> 1.0889646 | X26: =-'Income Statement'!Y7/'Balance Sheet'!U42 -> 1.0593246 | Y26: =-'Income Statement'!Z7/'Balance Sheet'!V42 -> 1.1057414 | Z26: =-'Income Statement'!AA7/'Balance Sheet'!V42 -> 3.958714 | AB26: =NA() -> #N/A
A27: Days Payable Outstanding (DPO) | B27: =IFERROR(365/B26,NA()) -> 669.98181 | C27: =IFERROR(365/C26,NA()) -> 644.39831 | D27: =IFERROR(365/D26,NA()) -> 497.67918 | E27: =IFERROR(365/E26,NA()) -> 424.50622 | F27: =IFERROR(365/F26,NA()) -> 113.9038 | G27: =IFERROR(365/G26,NA()) -> 507.91734 | H27: =IFERROR(365/H26,NA()) -> 473.68324 | I27: =IFERROR(365/I26,NA()) -> 448.60055 | ... Z27: =IFERROR(365/Z26,NA()) -> 92.201659 | AB27: =NA() -> #N/A
A28: Cash Conversion Cycle | B28: =B23+B25-B27 -> 381.3564 | C28: =C23+C25-C27 -> 462.53431 | D28: =D23+D25-D27 -> 561.2157 | E28: =E23+E25-E27 -> 526.7546 | F28: =F23+F25-F27 -> 143.51876 | G28: =G23+G25-G27 -> 493.5191 | H28: =H23+H25-H27 -> 612.25284 | I28: =I23+I25-I27 -> 453.08161 | ... Z28: =Z23+Z25-Z27 -> 160.08101 | AB28: =NA() -> #N/A
A29: V. Accurals Ratios
A30: Cash-flow-based accruals ratio | B30: =('Income Statement'!C24-'Cash Flow'!B39-'Cash Flow'!B48)/AVERAGE('Balance Sheet'!C19,$B$66) -> -0.0088181528 | C30: =IFERROR(('Income Statement'!D24-'Cash Flow'!C39-'Cash Flow'!C48)/AVERAGE('Balance Sheet'!D19,'Balance Sheet'!C19),"") -> 0.033892797 | D30: =IFERROR(('Income Statement'!E24-'Cash Flow'!D39-'Cash Flow'!D48)/AVERAGE('Balance Sheet'!E19,'Balance Sheet'!D19),"") -> 0.0047039357 | E30: =IFERROR(('Income Statement'!F24-'Cash Flow'!E39-'Cash Flow'!E48)/AVERAGE('Balance Sheet'!F19,'Balance Sheet'!E19),"") -> -0.016695109 | F30: =('Income Statement'!G24-'Cash Flow'!F39-'Cash Flow'!F48)/AVERAGE('Balance Sheet'!F19,$B$66) -> 0.013707284 | G30: =IFERROR(('Income Statement'!H24-'Cash Flow'!G39-'Cash Flow'!G48)/AVERAGE('Balance Sheet'!G19,'Balance Sheet'!F19),"") -> -0.0016707617 | H30: =IFERROR(('Income Statement'!I24-'Cash Flow'!H39-'Cash Flow'!H48)/AVERAGE('Balance Sheet'!H19,'Balance Sheet'!G19),"") -> 0.025821671 | I30: =IFERROR(('Income Statement'!J24-'Cash Flow'!I39-'Cash Flow'!I48)/AVERAGE('Balance Sheet'!I19,'Balance Sheet'!H19),"") -> -0.032525192 | J30: =IFERROR(('Income Statement'!K24-'Cash Flow'!J39-'Cash Flow'!J48)/AVERAGE('Balance Sheet'!J19,'Balance Sheet'!I19),"") -> 0.0034926833 | K30: =IFERROR(('Income Statement'!L24-'Cash Flow'!K39-'Cash Flow'!K48)/AVERAGE('Balance Sheet'!J19,'Balance Sheet'!F19),"") -> -0.0062876077 | L30: =IFERROR(('Income Statement'!M24-'Cash Flow'!L39-'Cash Flow'!L48)/AVERAGE('Balance Sheet'!K19,'Balance Sheet'!J19),"") -> 0.081323296 | M30: =IFERROR(('Income Statement'!N24-'Cash Flow'!M39-'Cash Flow'!M48)/AVERAGE('Balance Sheet'!L19,'Balance Sheet'!K19),"") -> 0.055354331 | N30: =IFERROR(('Income Statement'!O24-'Cash Flow'!N39-'Cash Flow'!N48)/AVERAGE('Balance Sheet'!M19,'Balance Sheet'!L19),"") -> 0.0015717044 | O30: =IFERROR(('Income Statement'!P24-'Cash Flow'!O39-'Cash Flow'!O48)/AVERAGE('Balance Sheet'!N19,'Balance Sheet'!M19),"") -> -0.022265531 | P30: =IFERROR(('Income Statement'!Q24-'Cash Flow'!P39-'Cash Flow'!P48)/AVERAGE('Balance Sheet'!N19,'Balance Sheet'!J19),"") -> 0.1124492 | Q30: =IFERROR(('Income Statement'!R24-'Cash Flow'!Q39-'Cash Flow'!Q48)/AVERAGE('Balance Sheet'!O19,'Balance Sheet'!N19),"") -> 0.054620294 | R30: =IFERROR(('Income Statement'!S24-'Cash Flow'!R39-'Cash Flow'!R48)/AVERAGE('Balance Sheet'!P19,'Balance Sheet'!O19),"") -> 0.019099563 | S30: =IFERROR(('Income Statement'!T24-'Cash Flow'!S39-'Cash Flow'!S48)/AVERAGE('Balance Sheet'!Q19,'Balance Sheet'!P19),"") -> -0.024575767 | T30: =IFERROR(('Income Statement'!U24-'Cash Flow'!T39-'Cash Flow'!T48)/AVERAGE('Balance Sheet'!R19,'Balance Sheet'!Q19),"") -> 0.032145678 | U30: =IFERROR(('Income Statement'!V24-'Cash Flow'!U39-'Cash Flow'!U48)/AVERAGE('Balance Sheet'!R19,'Balance Sheet'!N19),"") -> 0.078716871 | V30: =IFERROR(('Income Statement'!W24-'Cash Flow'!V39-'Cash Flow'!V48)/AVERAGE('Balance Sheet'!S19,'Balance Sheet'!R19),"") -> 0.071241242 | W30: =IFERROR(('Income Statement'!X24-'Cash Flow'!W39-'Cash Flow'!W48)/AVERAGE('Balance Sheet'!T19,'Balance Sheet'!S19),"") -> 0.063579325 | X30: =IFERROR(('Income Statement'!Y24-'Cash Flow'!X39-'Cash Flow'!X48)/AVERAGE('Balance Sheet'!U19,'Balance Sheet'!T19),"") -> -0.024214949 | Y30: =IFERROR(('Income Statement'!Z24-'Cash Flow'!Y39-'Cash Flow'!Y48)/AVERAGE('Balance Sheet'!V19,'Balance Sheet'!U19),"") -> 0.0043569503 | Z30: =IFERROR(('Income Statement'!AA24-'Cash Flow'!Z39-'Cash Flow'!Z48)/AVERAGE('Balance Sheet'!V19,'Balance Sheet'!R19),"") -> 0.11324137 | AB30: =NA() -> #N/A
A31: Balance-sheet-based accruals ratio | B31: =((('Balance Sheet'!C19-'Balance Sheet'!C17)-('Balance Sheet'!C45-'Balance Sheet'!C31-'Balance Sheet'!C32-'Balance Sheet'!C33-'Balance Sheet'!C38-'Balance Sheet'!C40))-$B$74)/AVERAGE((('Balance Sheet'!C19-'Balance Sheet'!C17)-('Balance Sheet'!C45-'Balance Sheet'!C31-'Balance Sheet'!C32-'Balance Sheet'!C33-'Balance Sheet'!C38-'Balance Sheet'!C40)),$B$74) -> 0.021136001 | C31: =IFERROR(((('Balance Sheet'!D19-'Balance Sheet'!D17)-('Balance Sheet'!D45-'Balance Sheet'!D31-'Balance Sheet'!D32-'Balance Sheet'!D33-'Balance Sheet'!D38-'Balance Sheet'!D40))-(('Balance Sheet'!C19-'Balance Sheet'!C17)-('Balance Sheet'!C45-'Balance Sheet'!C31-'Balance Sheet'!C32-'Balance Sheet'!C33-'Balance Sheet'!C38-'Balance Sheet'!C40)))/AVERAGE((('Balance Sheet'!D19-'Balance Sheet'!D17)-('Balance Sheet'!D45-'Balance Sheet'!D31-'Balance Sheet'!D32-'Balance Sheet'!D33-'Balance Sheet'!D38-'Balance Sheet'!D40)),(('Balance Sheet'!C19-'Balance Sheet'!C17)-('Balance Sheet'!C45-'Balance Sheet'!C31-'Balance Sheet'!C32-'Balance Sheet'!C33-'Balance Sheet'!C38-'Balance Sheet'!C40))),"") -> 0.031185549 | D31: =IFERROR(((('Balance Sheet'!E19-'Balance Sheet'!E17)-('Balance Sheet'!E45-'Balance Sheet'!E31-'Balance Sheet'!E32-'Balance Sheet'!E33-'Balance Sheet'!E38-'Balance Sheet'!E40))-(('Balance Sheet'!D19-'Balance Sheet'!D17)-('Balance Sheet'!D45-'Balance Sheet'!D31-'Balance Sheet'!D32-'Balance Sheet'!D33-'Balance Sheet'!D38-'Balance Sheet'!D40)))/AVERAGE((('Balance Sheet'!E19-'Balance Sheet'!E17)-('Balance Sheet'!E45-'Balance Sheet'!E31-'Balance Sheet'!E32-'Balance Sheet'!E33-'Balance Sheet'!E38-'Balance Sheet'!E40)),(('Balance Sheet'!D19-'Balance Sheet'!D17)-('Balance Sheet'!D45-'Balance Sheet'!D31-'Balance Sheet'!D32-'Balance Sheet'!D33-'Balance Sheet'!D38-'Balance Sheet'!D40))),"") -> 0.084707535 | E31: =IFERROR(((('Balance Sheet'!F19-'Balance Sheet'!F17)-('Balance Sheet'!F45-'Balance Sheet'!F31-'Balance Sheet'!F32-'Balance Sheet'!F33-'Balance Sheet'!F38-'Balance Sheet'!F40))-(('Balance Sheet'!E19-'Balance Sheet'!E17)-('Balance Sheet'!E45-'Balance Sheet'!E31-'Balance Sheet'!E32-'Balance Sheet'!E33-'Balance Sheet'!E38-'Balance Sheet'!E40)))/AVERAGE((('Balance Sheet'!F19-'Balance Sheet'!F17)-('Balance Sheet'!F45-'Balance Sheet'!F31-'Balance Sheet'!F32-'Balance Sheet'!F33-'Balance Sheet'!F38-'Balance Sheet'!F40)),(('Balance Sheet'!E19-'Balance Sheet'!E17)-('Balance Sheet'!E45-'Balance Sheet'!E31-'Balance Sheet'!E32-'Balance Sheet'!E33-'Balance Sheet'!E38-'Balance Sheet'!E40))),"") -> -0.029807841 | F31: =((('Balance Sheet'!F19-'Balance Sheet'!F17)-('Balance Sheet'!F45-'Balance Sheet'!F31-'Balance Sheet'!F32-'Balance Sheet'!F33-'Balance Sheet'!F38-'Balance Sheet'!F40))-$B$74)/AVERAGE((('Balance Sheet'!F19-'Balance Sheet'!F17)-('Balance Sheet'!F45-'Balance Sheet'!F31-'Balance Sheet'!F32-'Balance Sheet'!F33-'Balance Sheet'!F38-'Balance Sheet'!F40)),$B$74) -> 0.1071703 | G31: =IFERROR(((('Balance Sheet'!G19-'Balance Sheet'!G17)-('Balance Sheet'!G45-'Balance Sheet'!G31-'Balance Sheet'!G32-'Balance Sheet'!G33-'Balance Sheet'!G38-'Balance Sheet'!G40))-(('Balance Sheet'!F19-'Balance Sheet'!F17)-('Balance Sheet'!F45-'Balance Sheet'!F31-'Balance Sheet'!F32-'Balance Sheet'!F33-'Balance Sheet'!F38-'Balance Sheet'!F40)))/AVERAGE((('Balance Sheet'!G19-'Balance Sheet'!G17)-('Balance Sheet'!G45-'Balance Sheet'!G31-'Balance Sheet'!G32-'Balance Sheet'!G33-'Balance Sheet'!G38-'Balance Sheet'!G40)),(('Balance Sheet'!F19-'Balance Sheet'!F17)-('Balance Sheet'!F45-'Balance Sheet'!F31-'Balance Sheet'!F32-'Balance Sheet'!F33-'Balance Sheet'!F38-'Balance Sheet'!F40))),"") -> 0.018898426 | H31: =IFERROR(((('Balance Sheet'!H19-'Balance Sheet'!H17)-('Balance Sheet'!H45-'Balance Sheet'!H31-'Balance Sheet'!H32-'Balance Sheet'!H33-'Balance Sheet'!H38-'Balance Sheet'!H40))-(('Balance Sheet'!G19-'Balance Sheet'!G17)-('Balance Sheet'!G45-'Balance Sheet'!G31-'Balance Sheet'!G32-'Balance Sheet'!G33-'Balance Sheet'!G38-'Balance Sheet'!G40)))/AVERAGE((('Balance Sheet'!H19-'Balance Sheet'!H17)-('Balance Sheet'!H45-'Balance Sheet'!H31-'Balance Sheet'!H32-'Balance Sheet'!H33-'Balance Sheet'!H38-'Balance Sheet'!H40)),(('Balance Sheet'!G19-'Balance Sheet'!G17)-('Balance Sheet'!G45-'Balance Sheet'!G31-'Balance Sheet'!G32-'Balance Sheet'!G33-'Balance Sheet'!G38-'Balance Sheet'!G40))),"") -> 0.16050331 | I31: =IFERROR(((('Balance Sheet'!I19-'Balance Sheet'!I17)-('Balance Sheet'!I45-'Balance Sheet'!I31-'Balance Sheet'!I32-'Balance Sheet'!I33-'Balance Sheet'!I38-'Balance Sheet'!I40))-(('Balance Sheet'!H19-'Balance Sheet'!H17)-('Balance Sheet'!H45-'Balance Sheet'!H31-'Balance Sheet'!H32-'Balance Sheet'!H33-'Balance Sheet'!H38-'Balance Sheet'!H40)))/AVERAGE((('Balance Sheet'!I19-'Balance Sheet'!I17)-('Balance Sheet'!I45-'Balance Sheet'!I31-'Balance Sheet'!I32-'Balance Sheet'!I33-'Balance Sheet'!I38-'Balance Sheet'!I40)),(('Balance Sheet'!H19-'Balance Sheet'!H17)-('Balance Sheet'!H45-'Balance Sheet'!H31-'Balance Sheet'!H32-'Balance Sheet'!H33-'Balance Sheet'!H38-'Balance Sheet'!H40))),"") -> -0.042395899 | J31: =IFERROR(((('Balance Sheet'!J19-'Balance Sheet'!J17)-('Balance Sheet'!J45-'Balance Sheet'!J31-'Balance Sheet'!J32-'Balance Sheet'!J33-'Balance Sheet'!J38-'Balance Sheet'!J40))-(('Balance Sheet'!I19-'Balance Sheet'!I17)-('Balance Sheet'!I45-'Balance Sheet'!I31-'Balance Sheet'!I32-'Balance Sheet'!I33-'Balance Sheet'!I38-'Balance Sheet'!I40)))/AVERAGE((('Balance Sheet'!J19-'Balance Sheet'!J17)-('Balance Sheet'!J45-'Balance Sheet'!J31-'Balance Sheet'!J32-'Balance Sheet'!J33-'Balance Sheet'!J38-'Balance Sheet'!J40)),(('Balance Sheet'!I19-'Balance Sheet'!I17)-('Balance Sheet'!I45-'Balance Sheet'!I31-'Balance Sheet'!I32-'Balance Sheet'!I33-'Balance Sheet'!I38-'Balance Sheet'!I40))),"") -> 0.068473663 | K31: =IFERROR(((('Balance Sheet'!J19-'Balance Sheet'!J17)-('Balance Sheet'!J45-'Balance Sheet'!J31-'Balance Sheet'!J32-'Balance Sheet'!J33-'Balance Sheet'!J38-'Balance Sheet'!J40))-(('Balance Sheet'!F19-'Balance Sheet'!F17)-('Balance Sheet'!F45-'Balance Sheet'!F31-'Balance Sheet'!F32-'Balance Sheet'!F33-'Balance Sheet'!F38-'Balance Sheet'!F40)))/AVERAGE((('Balance Sheet'!J19-'Balance Sheet'!J17)-('Balance Sheet'!J45-'Balance Sheet'!J31-'Balance Sheet'!J32-'Balance Sheet'!J33-'Balance Sheet'!J38-'Balance Sheet'!J40)),(('Balance Sheet'!F19-'Balance Sheet'!F17)-('Balance Sheet'!F45-'Balance Sheet'!F31-'Balance Sheet'!F32-'Balance Sheet'!F33-'Balance Sheet'!F38-'Balance Sheet'!F40))),"") -> 0.2051226 | L31: =IFERROR(((('Balance Sheet'!K19-'Balance Sheet'!K17)-('Balance Sheet'!K45-'Balance Sheet'!K31-'Balance Sheet'!K32-'Balance Sheet'!K33-'Balance Sheet'!K38-'Balance Sheet'!K40))-(('Balance Sheet'!J19-'Balance Sheet'!J17)-('Balance Sheet'!J45-'Balance Sheet'!J31-'Balance Sheet'!J32-'Balance Sheet'!J33-'Balance Sheet'!J38-'Balance Sheet'!J40)))/AVERAGE((('Balance Sheet'!K19-'Balance Sheet'!K17)-('Balance Sheet'!K45-'Balance Sheet'!K31-'Balance Sheet'!K32-'Balance Sheet'!K33-'Balance Sheet'!K38-'Balance Sheet'!K40)),(('Balance Sheet'!J19-'Balance Sheet'!J17)-('Balance Sheet'!J45-'Balance Sheet'!J31-'Balance Sheet'!J32-'Balance Sheet'!J33-'Balance Sheet'!J38-'Balance Sheet'!J40))),"") -> 0.12254414 | M31: =IFERROR(((('Balance Sheet'!L19-'Balance Sheet'!L17)-('Balance Sheet'!L45-'Balance Sheet'!L31-'Balance Sheet'!L32-'Balance Sheet'!L33-'Balance Sheet'!L38-'Balance Sheet'!L40))-(('Balance Sheet'!K19-'Balance Sheet'!K17)-('Balance Sheet'!K45-'Balance Sheet'!K31-'Balance Sheet'!K32-'Balance Sheet'!K33-'Balance Sheet'!K38-'Balance Sheet'!K40)))/AVERAGE((('Balance Sheet'!L19-'Balance Sheet'!L17)-('Balance Sheet'!L45-'Balance Sheet'!L31-'Balance Sheet'!L32-'Balance Sheet'!L33-'Balance Sheet'!L38-'Balance Sheet'!L40)),(('Balance Sheet'!K19-'Balance Sheet'!K17)-('Balance Sheet'!K45-'Balance Sheet'!K31-'Balance Sheet'!K32-'Balance Sheet'!K33-'Balance Sheet'!K38-'Balance Sheet'!K40))),"") -> 0.089699733 | N31: =IFERROR(((('Balance Sheet'!M19-'Balance Sheet'!M17)-('Balance Sheet'!M45-'Balance Sheet'!M31-'Balance Sheet'!M32-'Balance Sheet'!M33-'Balance Sheet'!M38-'Balance Sheet'!M40))-(('Balance Sheet'!L19-'Balance Sheet'!L17)-('Balance Sheet'!L45-'Balance Sheet'!L31-'Balance Sheet'!L32-'Balance Sheet'!L33-'Balance Sheet'!L38-'Balance Sheet'!L40)))/AVERAGE((('Balance Sheet'!M19-'Balance Sheet'!M17)-('Balance Sheet'!M45-'Balance Sheet'!M31-'Balance Sheet'!M32-'Balance Sheet'!M33-'Balance Sheet'!M38-'Balance Sheet'!M40)),(('Balance Sheet'!L19-'Balance Sheet'!L17)-('Balance Sheet'!L45-'Balance Sheet'!L31-'Balance Sheet'!L32-'Balance Sheet'!L33-'Balance Sheet'!L38-'Balance Sheet'!L40))),"") -> -0.0011314772 | O31: =IFERROR(((('Balance Sheet'!N19-'Balance Sheet'!N17)-('Balance Sheet'!N45-'Balance Sheet'!N31-'Balance Sheet'!N32-'Balance Sheet'!N33-'Balance Sheet'!N38-'Balance Sheet'!N40))-(('Balance Sheet'!M19-'Balance Sheet'!M17)-('Balance Sheet'!M45-'Balance Sheet'!M31-'Balance Sheet'!M32-'Balance Sheet'!M33-'Balance Sheet'!M38-'Balance Sheet'!M40)))/AVERAGE((('Balance Sheet'!N19-'Balance Sheet'!N17)-('Balance Sheet'!N45-'Balance Sheet'!N31-'Balance Sheet'!N32-'Balance Sheet'!N33-'Balance Sheet'!N38-'Balance Sheet'!N40)),(('Balance Sheet'!M19-'Balance Sheet'!M17)-('Balance Sheet'!M45-'Balance Sheet'!M31-'Balance Sheet'!M32-'Balance Sheet'!M33-'Balance Sheet'!M38-'Balance Sheet'!M40))),"") -> -0.030923052 | P31: =IFERROR(((('Balance Sheet'!N19-'Balance Sheet'!N17)-('Balance Sheet'!N45-'Balance Sheet'!N31-'Balance Sheet'!N32-'Balance Sheet'!N33-'Balance Sheet'!N38-'Balance Sheet'!N40))-(('Balance Sheet'!J19-'Balance Sheet'!J17)-('Balance Sheet'!J45-'Balance Sheet'!J31-'Balance Sheet'!J32-'Balance Sheet'!J33-'Balance Sheet'!J38-'Balance Sheet'!J40)))/AVERAGE((('Balance Sheet'!N19-'Balance Sheet'!N17)-('Balance Sheet'!N45-'Balance Sheet'!N31-'Balance Sheet'!N32-'Balance Sheet'!N33-'Balance Sheet'!N38-'Balance Sheet'!N40)),(('Balance Sheet'!J19-'Balance Sheet'!J17)-('Balance Sheet'!J45-'Balance Sheet'!J31-'Balance Sheet'!J32-'Balance Sheet'!J33-'Balance Sheet'!J38-'Balance Sheet'!J40))),"") -> 0.17991313 | Q31: =IFERROR(((('Balance Sheet'!O19-'Balance Sheet'!O17)-('Balance Sheet'!O45-'Balance Sheet'!O31-'Balance Sheet'!O32-'Balance Sheet'!O33-'Balance Sheet'!O38-'Balance Sheet'!O40))-(('Balance Sheet'!N19-'Balance Sheet'!N17)-('Balance Sheet'!N45-'Balance Sheet'!N31-'Balance Sheet'!N32-'Balance Sheet'!N33-'Balance Sheet'!N38-'Balance Sheet'!N40)))/AVERAGE((('Balance Sheet'!O19-'Balance Sheet'!O17)-('Balance Sheet'!O45-'Balance Sheet'!O31-'Balance Sheet'!O32-'Balance Sheet'!O33-'Balance Sheet'!O38-'Balance Sheet'!O40)),(('Balance Sheet'!N19-'Balance Sheet'!N17)-('Balance Sheet'!N45-'Balance Sheet'!N31-'Balance Sheet'!N32-'Balance Sheet'!N33-'Balance Sheet'!N38-'Balance Sheet'!N40))),"") -> 0.040148434 | R31: =IFERROR(((('Balance Sheet'!P19-'Balance Sheet'!P17)-('Balance Sheet'!P45-'Balance Sheet'!P31-'Balance Sheet'!P32-'Balance Sheet'!P33-'Balance Sheet'!P38-'Balance Sheet'!P40))-(('Balance Sheet'!O19-'Balance Sheet'!O17)-('Balance Sheet'!O45-'Balance Sheet'!O31-'Balance Sheet'!O32-'Balance Sheet'!O33-'Balance Sheet'!O38-'Balance Sheet'!O40)))/AVERAGE((('Balance Sheet'!P19-'Balance Sheet'!P17)-('Balance Sheet'!P45-'Balance Sheet'!P31-'Balance Sheet'!P32-'Balance Sheet'!P33-'Balance Sheet'!P38-'Balance Sheet'!P40)),(('Balance Sheet'!O19-'Balance Sheet'!O17)-('Balance Sheet'!O45-'Balance Sheet'!O31-'Balance Sheet'!O32-'Balance Sheet'!O33-'Balance Sheet'!O38-'Balance Sheet'!O40))),"") -> 0.10790527 | S31: =IFERROR(((('Balance Sheet'!Q19-'Balance Sheet'!Q17)-('Balance Sheet'!Q45-'Balance Sheet'!Q31-'Balance Sheet'!Q32-'Balance Sheet'!Q33-'Balance Sheet'!Q38-'Balance Sheet'!Q40))-(('Balance Sheet'!P19-'Balance Sheet'!P17)-('Balance Sheet'!P45-'Balance Sheet'!P31-'Balance Sheet'!P32-'Balance Sheet'!P33-'Balance Sheet'!P38-'Balance Sheet'!P40)))/AVERAGE((('Balance Sheet'!Q19-'Balance Sheet'!Q17)-('Balance Sheet'!Q45-'Balance Sheet'!Q31-'Balance Sheet'!Q32-'Balance Sheet'!Q33-'Balance Sheet'!Q38-'Balance Sheet'!Q40)),(('Balance Sheet'!P19-'Balance Sheet'!P17)-('Balance Sheet'!P45-'Balance Sheet'!P31-'Balance Sheet'!P32-'Balance Sheet'!P33-'Balance Sheet'!P38-'Balance Sheet'!P40))),"") -> 0.1835371 | T31: =IFERROR(((('Balance Sheet'!R19-'Balance Sheet'!R17)-('Balance Sheet'!R45-'Balance Sheet'!R31-'Balance Sheet'!R32-'Balance Sheet'!R33-'Balance Sheet'!R38-'Balance Sheet'!R40))-(('Balance Sheet'!Q19-'Balance Sheet'!Q17)-('Balance Sheet'!Q45-'Balance Sheet'!Q31-'Balance Sheet'!Q32-'Balance Sheet'!Q33-'Balance Sheet'!Q38-'Balance Sheet'!Q40)))/AVERAGE((('Balance Sheet'!R19-'Balance Sheet'!R17)-('Balance Sheet'!R45-'Balance Sheet'!R31-'Balance Sheet'!R32-'Balance Sheet'!R33-'Balance Sheet'!R38-'Balance Sheet'!R40)),(('Balance Sheet'!Q19-'Balance Sheet'!Q17)-('Balance Sheet'!Q45-'Balance Sheet'!Q31-'Balance Sheet'!Q32-'Balance Sheet'!Q33-'Balance Sheet'!Q38-'Balance Sheet'!Q40))),"") -> -0.033118657 | U31: =IFERROR(((('Balance Sheet'!R19-'Balance Sheet'!R17)-('Balance Sheet'!R45-'Balance Sheet'!R31-'Balance Sheet'!R32-'Balance Sheet'!R33-'Balance Sheet'!R38-'Balance Sheet'!R40))-(('Balance Sheet'!N19-'Balance Sheet'!N17)-('Balance Sheet'!N45-'Balance Sheet'!N31-'Balance Sheet'!N32-'Balance Sheet'!N33-'Balance Sheet'!N38-'Balance Sheet'!N40)))/AVERAGE((('Balance Sheet'!R19-'Balance Sheet'!R17)-('Balance Sheet'!R45-'Balance Sheet'!R31-'Balance Sheet'!R32-'Balance Sheet'!R33-'Balance Sheet'!R38-'Balance Sheet'!R40)),(('Balance Sheet'!N19-'Balance Sheet'!N17)-('Balance Sheet'!N45-'Balance Sheet'!N31-'Balance Sheet'!N32-'Balance Sheet'!N33-'Balance Sheet'!N38-'Balance Sheet'!N40))),"") -> 0.29688725 | V31: =IFERROR(((('Balance Sheet'!S19-'Balance Sheet'!S17)-('Balance Sheet'!S45-'Balance Sheet'!S31-'Balance Sheet'!S32-'Balance Sheet'!S33-'Balance Sheet'!S38-'Balance Sheet'!S40))-(('Balance Sheet'!R19-'Balance Sheet'!R17)-('Balance Sheet'!R45-'Balance Sheet'!R31-'Balance Sheet'!R32-'Balance Sheet'!R33-'Balance Sheet'!R38-'Balance Sheet'!R40)))/AVERAGE((('Balance Sheet'!S19-'Balance Sheet'!S17)-('Balance Sheet'!S45-'Balance Sheet'!S31-'Balance Sheet'!S32-'Balance Sheet'!S33-'Balance Sheet'!S38-'Balance Sheet'!S40)),(('Balance Sheet'!R19-'Balance Sheet'!R17)-('Balance Sheet'!R45-'Balance Sheet'!R31-'Balance Sheet'!R32-'Balance Sheet'!R33-'Balance Sheet'!R38-'Balance Sheet'!R40))),"") -> 0.10750325 | W31: =IFERROR(((('Balance Sheet'!T19-'Balance Sheet'!T17)-('Balance Sheet'!T45-'Balance Sheet'!T31-'Balance Sheet'!T32-'Balance Sheet'!T33-'Balance Sheet'!T38-'Balance Sheet'!T40))-(('Balance Sheet'!S19-'Balance Sheet'!S17)-('Balance Sheet'!S45-'Balance Sheet'!S31-'Balance Sheet'!S32-'Balance Sheet'!S33-'Balance Sheet'!S38-'Balance Sheet'!S40)))/AVERAGE((('Balance Sheet'!T19-'Balance Sheet'!T17)-('Balance Sheet'!T45-'Balance Sheet'!T31-'Balance Sheet'!T32-'Balance Sheet'!T33-'Balance Sheet'!T38-'Balance Sheet'!T40)),(('Balance Sheet'!S19-'Balance Sheet'!S17)-('Balance Sheet'!S45-'Balance Sheet'!S31-'Balance Sheet'!S32-'Balance Sheet'!S33-'Balance Sheet'!S38-'Balance Sheet'!S40))),"") -> 0.093108404 | X31: =IFERROR(((('Balance Sheet'!U19-'Balance Sheet'!U17)-('Balance Sheet'!U45-'Balance Sheet'!U31-'Balance Sheet'!U32-'Balance Sheet'!U33-'Balance Sheet'!U38-'Balance Sheet'!U40))-(('Balance Sheet'!T19-'Balance Sheet'!T17)-('Balance Sheet'!T45-'Balance Sheet'!T31-'Balance Sheet'!T32-'Balance Sheet'!T33-'Balance Sheet'!T38-'Balance Sheet'!T40)))/AVERAGE((('Balance Sheet'!U19-'Balance Sheet'!U17)-('Balance Sheet'!U45-'Balance Sheet'!U31-'Balance Sheet'!U32-'Balance Sheet'!U33-'Balance Sheet'!U38-'Balance Sheet'!U40)),(('Balance Sheet'!T19-'Balance Sheet'!T17)-('Balance Sheet'!T45-'Balance Sheet'!T31-'Balance Sheet'!T32-'Balance Sheet'!T33-'Balance Sheet'!T38-'Balance Sheet'!T40))),"") -> -0.041698304 | Y31: =IFERROR(((('Balance Sheet'!V19-'Balance Sheet'!V17)-('Balance Sheet'!V45-'Balance Sheet'!V31-'Balance Sheet'!V32-'Balance Sheet'!V33-'Balance Sheet'!V38-'Balance Sheet'!V40))-(('Balance Sheet'!U19-'Balance Sheet'!U17)-('Balance Sheet'!U45-'Balance Sheet'!U31-'Balance Sheet'!U32-'Balance Sheet'!U33-'Balance Sheet'!U38-'Balance Sheet'!U40)))/AVERAGE((('Balance Sheet'!V19-'Balance Sheet'!V17)-('Balance Sheet'!V45-'Balance Sheet'!V31-'Balance Sheet'!V32-'Balance Sheet'!V33-'Balance Sheet'!V38-'Balance Sheet'!V40)),(('Balance Sheet'!U19-'Balance Sheet'!U17)-('Balance Sheet'!U45-'Balance Sheet'!U31-'Balance Sheet'!U32-'Balance Sheet'!U33-'Balance Sheet'!U38-'Balance Sheet'!U40))),"") -> -0.00030975344 | Z31: =IFERROR(((('Balance Sheet'!V19-'Balance Sheet'!V17)-('Balance Sheet'!V45-'Balance Sheet'!V31-'Balance Sheet'!V32-'Balance Sheet'!V33-'Balance Sheet'!V38-'Balance Sheet'!V40))-(('Balance Sheet'!R19-'Balance Sheet'!R17)-('Balance Sheet'!R45-'Balance Sheet'!R31-'Balance Sheet'!R32-'Balance Sheet'!R33-'Balance Sheet'!R38-'Balance Sheet'!R40)))/AVERAGE((('Balance Sheet'!V19-'Balance Sheet'!V17)-('Balance Sheet'!V45-'Balance Sheet'!V31-'Balance Sheet'!V32-'Balance Sheet'!V33-'Balance Sheet'!V38-'Balance Sheet'!V40)),(('Balance Sheet'!R19-'Balance Sheet'!R17)-('Balance Sheet'!R45-'Balance Sheet'!R31-'Balance Sheet'!R32-'Balance Sheet'!R33-'Balance Sheet'!R38-'Balance Sheet'!R40))),"") -> 0.15843595 | AB31: =NA() -> #N/A
A32: ratio of operating cash flow before interest and taxes to operating income | B32: =IFERROR('Cash Flow'!B33/'Income Statement'!C16,"") -> 2.4973061 | C32: =IFERROR('Cash Flow'!C33/'Income Statement'!D16,"") -> -13.21289 | D32: =IFERROR('Cash Flow'!D33/'Income Statement'!E16,"") -> -3.3488211 | E32: =IFERROR('Cash Flow'!E33/'Income Statement'!F16,"") -> 6.7298602 | F32: =IFERROR('Cash Flow'!F33/'Income Statement'!G16,"") -> 2.7594422 | G32: =IFERROR('Cash Flow'!G33/'Income Statement'!H16,"") -> 2.716146 | H32: =IFERROR('Cash Flow'!H33/'Income Statement'!I16,"") -> 3.4288696 | I32: =IFERROR('Cash Flow'!I33/'Income Statement'!J16,"") -> -1.4611004 | ... Z32: =IFERROR('Cash Flow'!Z33/'Income Statement'!AA16,"") -> 0.57883063 | AB32: =IFERROR('Cash Flow'!AB33/'Income Statement'!AB16,"") -> -3.1504059
A33: VI. FREE CASH FLOW
A34: FCFE | B34: =IFERROR('Cash Flow'!B39+'Cash Flow'!B41+'Cash Flow'!B50+'Cash Flow'!B54,"") -> 6633717 | C34: =IFERROR('Cash Flow'!C39+'Cash Flow'!C41+'Cash Flow'!C50+'Cash Flow'!C54,"") -> 35255729 | D34: =IFERROR('Cash Flow'!D39+'Cash Flow'!D41+'Cash Flow'!D50+'Cash Flow'!D54,"") -> -4978537 | E34: =IFERROR('Cash Flow'!E39+'Cash Flow'!E41+'Cash Flow'!E50+'Cash Flow'!E54,"") -> -6908155 | F34: =IFERROR('Cash Flow'!F39+'Cash Flow'!F41+'Cash Flow'!F50+'Cash Flow'!F54,"") -> 30002754 | G34: =IFERROR('Cash Flow'!G39+'Cash Flow'!G41+'Cash Flow'!G50+'Cash Flow'!G54,"") -> 121044042 | H34: =IFERROR('Cash Flow'!H39+'Cash Flow'!H41+'Cash Flow'!H50+'Cash Flow'!H54,"") -> -28946657 | I34: =IFERROR('Cash Flow'!I39+'Cash Flow'!I41+'Cash Flow'!I50+'Cash Flow'!I54,"") -> 173129162 | ... Z34: =IFERROR('Cash Flow'!Z39+'Cash Flow'!Z41+'Cash Flow'!Z50+'Cash Flow'!Z54,"") -> 5969391 | AB34: =IFERROR('Cash Flow'!AB39+'Cash Flow'!AB41+'Cash Flow'!AB50+'Cash Flow'!AB54,"") -> 238969528
A35: FCF | B35: =IFERROR('Cash Flow'!B39+'Cash Flow'!B41,"") -> 11476511 | C35: =IFERROR('Cash Flow'!C39+'Cash Flow'!C41,"") -> -116450050 | D35: =IFERROR('Cash Flow'!D39+'Cash Flow'!D41,"") -> -20730409 | E35: =IFERROR('Cash Flow'!E39+'Cash Flow'!E41,"") -> 55645810 | F35: =IFERROR('Cash Flow'!F39+'Cash Flow'!F41,"") -> -70058138 | G35: =IFERROR('Cash Flow'!G39+'Cash Flow'!G41,"") -> 39278853 | H35: =IFERROR('Cash Flow'!H39+'Cash Flow'!H41,"") -> -176190432 | I35: =IFERROR('Cash Flow'!I39+'Cash Flow'!I41,"") -> 130117512 | ... Z35: =IFERROR('Cash Flow'!Z39+'Cash Flow'!Z41,"") -> -662737422 | AB35: =IFERROR('Cash Flow'!AB39+'Cash Flow'!AB41,"") -> 294675617
A36: VII. CASH QUALITY RATIOS
A37: Cash Realization (OCF / Net Income) | B37: =IFERROR('Cash Flow'!B39/'Income Statement'!C24,"") -> -1.5205286 | C37: =IFERROR('Cash Flow'!C39/'Income Statement'!D24,"") -> 23.198892 | D37: =IFERROR('Cash Flow'!D39/'Income Statement'!E24,"") -> 0.95255431 | E37: =IFERROR('Cash Flow'!E39/'Income Statement'!F24,"") -> -912.72597 | F37: =IFERROR('Cash Flow'!F39/'Income Statement'!G24,"") -> 0.20266036 | G37: =IFERROR('Cash Flow'!G39/'Income Statement'!H24,"") -> 2.069659 | H37: =IFERROR('Cash Flow'!H39/'Income Statement'!I24,"") -> 2.7708695 | I37: =IFERROR('Cash Flow'!I39/'Income Statement'!J24,"") -> -26.446218 | ... Z37: =IFERROR('Cash Flow'!Z39/'Income Statement'!AA24,"") -> -0.75579544 | AB37: =IFERROR('Cash Flow'!AB39/'Income Statement'!AB24,"") -> -1.585662
A38: Operating Cash Margin (OCF / Revenue) | B38: =IFERROR('Cash Flow'!B39/'Income Statement'!C6,"") -> 0.03584592 | C38: =IFERROR('Cash Flow'!C39/'Income Statement'!D6,"") -> -0.15414329 | D38: =IFERROR('Cash Flow'!D39/'Income Statement'!E6,"") -> -0.0068264172 | E38: =IFERROR('Cash Flow'!E39/'Income Statement'!F6,"") -> 0.10524675 | F38: =IFERROR('Cash Flow'!F39/'Income Statement'!G6,"") -> -0.0017899378 | G38: =IFERROR('Cash Flow'!G39/'Income Statement'!H6,"") -> 0.09253423 | H38: =IFERROR('Cash Flow'!H39/'Income Statement'!I6,"") -> -0.22143675 | I38: =IFERROR('Cash Flow'!I39/'Income Statement'!J6,"") -> 0.16349987 | ... Z38: =IFERROR('Cash Flow'!Z39/'Income Statement'!AA6,"") -> -0.02511325 | AB38: =IFERROR('Cash Flow'!AB39/'Income Statement'!AB6,"") -> 0.17159238
A39: CapEx Coverage (OCF / |CapEx|) | B39: =IFERROR('Cash Flow'!B39/ABS('Cash Flow'!B41),"") -> 2.1420555 | C39: =IFERROR('Cash Flow'!C39/ABS('Cash Flow'!C41),"") -> -5.3237838 | D39: =IFERROR('Cash Flow'!D39/ABS('Cash Flow'!D41),"") -> -0.28831218 | E39: =IFERROR('Cash Flow'!E39/ABS('Cash Flow'!E41),"") -> 3.678628 | F39: =IFERROR('Cash Flow'!F39/ABS('Cash Flow'!F41),"") -> -0.07239372 | G39: =IFERROR('Cash Flow'!G39/ABS('Cash Flow'!G41),"") -> 2.3221853 | H39: =IFERROR('Cash Flow'!H39/ABS('Cash Flow'!H41),"") -> -9.9925839 | I39: =IFERROR('Cash Flow'!I39/ABS('Cash Flow'!I41),"") -> 14.539288 | ... Z39: =IFERROR('Cash Flow'!Z39/ABS('Cash Flow'!Z41),"") -> -0.4198621 | AB39: =IFERROR('Cash Flow'!AB39/ABS('Cash Flow'!AB41),"") -> 6.0824861
A64: Note 2020
A65: ── FY-2020 Opening Balances (from FY-2020 Audited FS) ──
A66: Total Assets (FY-2020) | B66: 3252906060
A67: Cash & Equivalents (FY-2020) | B67: 119446611
A68: Total Liabilities (FY-2020) | B68: 1686845794
A69: LT Loans non-current (FY-2020) | B69: 34910579
A70: Lease NC liab (FY-2020) | B70: 2335456
A71: LT Notes Payable (FY-2020) | B71: 0
A72: Bank Overdrafts (FY-2020) | B72: 717179376
A73: Loans Current Portion (FY-2020) | B73: 11011000
A74: NOA (FY-2020) — calculated | B74: =(B66-B67)-(B68-B69-B70-B71-B72-B73) -> 2212050066
A113: =A41 -> 0 | B113: =B41 -> 0 | C113: =C41 -> 0 | D113: =D41 -> 0 | E113: =E41 -> 0 | F113: =F41 -> 0
A114: =A45 -> 0 | B114: =B45 -> 0 | C114: =C45 -> 0 | D114: =D45 -> 0 | E114: =E45 -> 0 | F114: =F45 -> 0
A115: =A46 -> 0 | B115: =B46 -> 0 | C115: =C46 -> 0 | D115: =D46 -> 0 | E115: =E46 -> 0 | F115: =F46 -> 0
A117: =A41 -> 0 | B117: =B41 -> 0 | C117: =C41 -> 0 | D117: =D41 -> 0 | E117: =E41 -> 0 | F117: =F41 -> 0
A118: =A47 -> 0 | B118: =B47 -> 0 | C118: =C47 -> 0 | D118: =D47 -> 0 | E118: =E47 -> 0 | F118: =F47 -> 0
A119: =A48 -> 0 | B119: =B48 -> 0 | C119: =C48 -> 0 | D119: =D48 -> 0 | E119: =E48 -> 0 | F119: =F48 -> 0
A120: =A49 -> 0 | B120: =B49 -> 0 | C120: =C49 -> 0 | D120: =D49 -> 0 | E120: =E49 -> 0 | F120: =F49 -> 0
A122: =A41 -> 0 | B122: =B41 -> 0 | C122: =C41 -> 0 | D122: =D41 -> 0 | E122: =E41 -> 0 | F122: =F41 -> 0
A123: =A50 -> 0 | B123: =B50 -> 0 | C123: =C50 -> 0 | D123: =D50 -> 0 | E123: =E50 -> 0 | F123: =F50 -> 0
A124: =A51 -> 0 | B124: =B51 -> 0 | C124: =C51 -> 0 | D124: =D51 -> 0 | E124: =E51 -> 0 | F124: =F51 -> 0
A125: =A52 -> 0 | B125: =B52 -> 0 | C125: =C52 -> 0 | D125: =D52 -> 0 | E125: =E52 -> 0 | F125: =F52 -> 0
A127: =A41 -> 0 | B127: =B41 -> 0 | C127: =C41 -> 0 | D127: =D41 -> 0 | E127: =E41 -> 0 | F127: =F41 -> 0
A128: =A53 -> 0 | B128: =B53 -> 0 | C128: =C53 -> 0 | D128: =D53 -> 0 | E128: =E53 -> 0 | F128: =F53 -> 0
A129: =A54 -> 0 | B129: =B54 -> 0 | C129: =C54 -> 0 | D129: =D54 -> 0 | E129: =E54 -> 0 | F129: =F54 -> 0
A130: =A55 -> 0 | B130: =B55 -> 0 | C130: =C55 -> 0 | D130: =D55 -> 0 | E130: =E55 -> 0 | F130: =F55 -> 0
A131: =A56 -> 0 | B131: =B56 -> 0 | C131: =C56 -> 0 | D131: =D56 -> 0 | E131: =E56 -> 0 | F131: =F56 -> 0
A133: =A41 -> 0 | B133: =B41 -> 0 | C133: =C41 -> 0 | D133: =D41 -> 0 | E133: =E41 -> 0 | F133: =F41 -> 0
A134: =A57 -> 0 | B134: =B57 -> 0 | C134: =C57 -> 0 | D134: =D57 -> 0 | E134: =E57 -> 0 | F134: =F57 -> 0
A135: =A58 -> 0 | B135: =B58 -> 0 | C135: =C58 -> 0 | D135: =D58 -> 0 | E135: =E58 -> 0 | F135: =F58 -> 0
